[
  {
    "country": "Hungary",
    "retailer": "Douglas_HU",
    "parsing_config": "./retailer_config/Douglas/douglas_parsing.json",
    "gcloud_path": "crawl_data/Hungary/Douglas_HU/",
    "department": "Promotions",
    "category": "Promotions",
    "page": "Promotions",
    "page_url": "https://www.douglas.hu/c/akciok/",
    "file_name": "Hungary_DOUGLAS_HU_PROMOTIONS_PROMOTIONS_PROMOTIONS"
  },
  {
    "country": "Hungary",
    "retailer": "Douglas_HU",
    "parsing_config": "./retailer_config/Douglas/douglas_parsing.json",
    "gcloud_path": "crawl_data/Hungary/Douglas_HU/",
    "department": "Promotions",
    "category": "DISCOUNT NEWSPAPER",
    "page": "DISCOUNT NEWSPAPER",
    "page_url": "https://www.douglas.hu/c/akciok/akcios-ujsag/",
    "file_name": "Hungary_DOUGLAS_HU_PROMOTIONS_DISCOUNT|sp|NEWSPAPER_DISCOUNT|sp|NEWSPAPER"
  },
  {
    "country": "Hungary",
    "retailer": "Douglas_HU",
    "parsing_config": "./retailer_config/Douglas/douglas_parsing.json",
    "gcloud_path": "crawl_data/Hungary/Douglas_HU/",
    "department": "Promotions",
    "category": "PERFUME SALE",
    "page": "PERFUME SALE",
    "page_url": "https://www.douglas.hu/c/akciok/parfum-akcio/",
    "file_name": "Hungary_DOUGLAS_HU_PROMOTIONS_PERFUME|sp|SALE_PERFUME|sp|SALE"
  },
  {
    "country": "Hungary",
    "retailer": "Douglas_HU",
    "parsing_config": "./retailer_config/Douglas/douglas_parsing.json",
    "gcloud_path": "crawl_data/Hungary/Douglas_HU/",
    "department": "Promotions",
    "category": "PERFUME SALE",
    "page": "Womens perfume sale",
    "page_url": "https://www.douglas.hu/c/akciok/parfum-akcio/noi-parfum-akcio/",
    "file_name": "Hungary_DOUGLAS_HU_PROMOTIONS_PERFUME|sp|SALE_Women|sq|s|sp|perfume|sp|sale"
  },
  {
    "country": "Hungary",
    "retailer": "Douglas_HU",
    "parsing_config": "./retailer_config/Douglas/douglas_parsing.json",
    "gcloud_path": "crawl_data/Hungary/Douglas_HU/",
    "department": "Promotions",
    "category": "PERFUME SALE",
    "page": "Men's perfume sale",
    "page_url": "https://www.douglas.hu/c/akciok/parfum-akcio/ferfi-parfum-akcio/",
    "file_name": "Hungary_DOUGLAS_HU_PROMOTIONS_PERFUME|sp|SALE_Men|sq|s|sp|perfume|sp|sale"
  },
  {
    "country": "Hungary",
    "retailer": "Douglas_HU",
    "parsing_config": "./retailer_config/Douglas/douglas_parsing.json",
    "gcloud_path": "crawl_data/Hungary/Douglas_HU/",
    "department": "Promotions",
    "category": "PERFUME SALE",
    "page": "Bestsellers",
    "page_url": "https://www.douglas.hu/c/akciok/parfum-akcio/bestseller/",
    "file_name": "Hungary_DOUGLAS_HU_PROMOTIONS_PERFUME|sp|SALE_Bestseller"
  },
  {
    "country": "Hungary",
    "retailer": "Douglas_HU",
    "parsing_config": "./retailer_config/Douglas/douglas_parsing.json",
    "gcloud_path": "crawl_data/Hungary/Douglas_HU/",
    "department": "Promotions",
    "category": "SKIN CARE SALE",
    "page": "SKIN CARE SALE",
    "page_url": "https://www.douglas.hu/c/akciok/borapolas-akcio/",
    "file_name": "Hungary_DOUGLAS_HU_PROMOTIONS_SKIN|sp|CARE|sp|SALE_SKIN|sp|CARE|sp|SALE"
  },
  {
    "country": "Hungary",
    "retailer": "Douglas_HU",
    "parsing_config": "./retailer_config/Douglas/douglas_parsing.json",
    "gcloud_path": "crawl_data/Hungary/Douglas_HU/",
    "department": "Promotions",
    "category": "MAKE-UP ACTION",
    "page": "MAKE-UP ACTION",
    "page_url": "https://www.douglas.hu/c/akciok/make-up-akcio/",
    "file_name": "Hungary_DOUGLAS_HU_PROMOTIONS_MAKE|h|UP|sp|ACTION_MAKE|h|UP|sp|ACTION"
  },
  {
    "country": "Hungary",
    "retailer": "Douglas_HU",
    "parsing_config": "./retailer_config/Douglas/douglas_parsing.json",
    "gcloud_path": "crawl_data/Hungary/Douglas_HU/",
    "department": "Promotions",
    "category": "BRAND WEEK",
    "page": "BRAND WEEK",
    "page_url": "https://www.douglas.hu/c/akciok/markahet/",
    "file_name": "Hungary_DOUGLAS_HU_PROMOTIONS_BRAND|sp|WEEK_BRAND|sp|WEEK"
  },
  {
    "country": "Hungary",
    "retailer": "Douglas_HU",
    "parsing_config": "./retailer_config/Douglas/douglas_parsing.json",
    "gcloud_path": "crawl_data/Hungary/Douglas_HU/",
    "department": "Promotions",
    "category": "CHARMING OFFER",
    "page": "CHARMING OFFER",
    "page_url": "https://www.douglas.hu/c/akciok/elbuvolo-ajanlat/",
    "file_name": "Hungary_DOUGLAS_HU_PROMOTIONS_CHARMING|sp|OFFER_CHARMING|sp|OFFER"
  },
  {
    "country": "Hungary",
    "retailer": "Douglas_HU",
    "parsing_config": "./retailer_config/Douglas/douglas_parsing.json",
    "gcloud_path": "crawl_data/Hungary/Douglas_HU/",
    "department": "Promotions",
    "category": "OUTLET - DISCONTINUED PRODUCTS",
    "page": "OUTLET - DISCONTINUED PRODUCTS",
    "page_url": "https://www.douglas.hu/c/akciok/outlet-kifuto-termekek/",
    "file_name": "Hungary_DOUGLAS_HU_PROMOTIONS_OUTLET|sp||h||sp|DISCONTINUED|sp|PRODUCTS_OUTLET|sp||h||sp|DISCONTINUED|sp|PRODUCTS"
  },
  {
    "country": "Hungary",
    "retailer": "Douglas_HU",
    "parsing_config": "./retailer_config/Douglas/douglas_parsing.json",
    "gcloud_path": "crawl_data/Hungary/Douglas_HU/",
    "department": "Promotions",
    "category": "WORLD BRANDS WITH DISCOUNTS",
    "page": "WORLD BRANDS WITH DISCOUNTS",
    "page_url": "https://www.douglas.hu/c/akciok/vilagmarkak-kedvezmenyekkel/",
    "file_name": "Hungary_DOUGLAS_HU_PROMOTIONS_WORLD|sp|BRANDS|sp|WITH|sp|DISCOUNTS_WORLD|sp|BRANDS|sp|WITH|sp|DISCOUNTS"
  },
  {
    "country": "Hungary",
    "retailer": "Douglas_HU",
    "parsing_config": "./retailer_config/Douglas/douglas_parsing.json",
    "gcloud_path": "crawl_data/Hungary/Douglas_HU/",
    "department": "Brands",
    "category": "Clinique",
    "page": "Clinique",
    "page_url": "https://www.douglas.hu/b/clinique/",
    "file_name": "Hungary_DOUGLAS_HU_BRANDS_Clinique_Clinique"
  },
  {
    "country": "Hungary",
    "retailer": "Douglas_HU",
    "parsing_config": "./retailer_config/Douglas/douglas_parsing.json",
    "gcloud_path": "crawl_data/Hungary/Douglas_HU/",
    "department": "Brands",
    "category": "DIOR",
    "page": "DIOR",
    "page_url": "https://www.douglas.hu/b/dior/",
    "file_name": "Hungary_DOUGLAS_HU_BRANDS_DIOR_DIOR"
  },
  {
    "country": "Hungary",
    "retailer": "Douglas_HU",
    "parsing_config": "./retailer_config/Douglas/douglas_parsing.json",
    "gcloud_path": "crawl_data/Hungary/Douglas_HU/",
    "department": "Brands",
    "category": "Estee Lauder",
    "page": "Estee Lauder",
    "page_url": "https://www.douglas.hu/b/estee-lauder/",
    "file_name": "Hungary_DOUGLAS_HU_BRANDS_Estee|sp|Lauder_Estee|sp|Lauder"
  },
  {
    "country": "Hungary",
    "retailer": "Douglas_HU",
    "parsing_config": "./retailer_config/Douglas/douglas_parsing.json",
    "gcloud_path": "crawl_data/Hungary/Douglas_HU/",
    "department": "Brands",
    "category": "Giorgio Armani",
    "page": "Giorgio Armani",
    "page_url": "https://www.douglas.hu/b/giorgio-armani/",
    "file_name": "Hungary_DOUGLAS_HU_BRANDS_Giorgio|sp|Armani_Giorgio|sp|Armani"
  },
  {
    "country": "Hungary",
    "retailer": "Douglas_HU",
    "parsing_config": "./retailer_config/Douglas/douglas_parsing.json",
    "gcloud_path": "crawl_data/Hungary/Douglas_HU/",
    "department": "Brands",
    "category": "The sea",
    "page": "The sea",
    "page_url": "https://www.douglas.hu/b/la-mer/",
    "file_name": "Hungary_DOUGLAS_HU_BRANDS_The|sp|sea_The|sp|sea"
  },
  {
    "country": "Hungary",
    "retailer": "Douglas_HU",
    "parsing_config": "./retailer_config/Douglas/douglas_parsing.json",
    "gcloud_path": "crawl_data/Hungary/Douglas_HU/",
    "department": "Brands",
    "category": "Lancome",
    "page": "Lancome",
    "page_url": "https://www.douglas.hu/b/lancome/",
    "file_name": "Hungary_DOUGLAS_HU_BRANDS_Lancome_Lancome"
  },
  {
    "country": "Hungary",
    "retailer": "Douglas_HU",
    "parsing_config": "./retailer_config/Douglas/douglas_parsing.json",
    "gcloud_path": "crawl_data/Hungary/Douglas_HU/",
    "department": "Brands",
    "category": "Paco Rabanne",
    "page": "Paco Rabanne",
    "page_url": "https://www.douglas.hu/b/paco-rabanne/",
    "file_name": "Hungary_DOUGLAS_HU_BRANDS_Paco|sp|Rabanne_Paco|sp|Rabanne"
  },
  {
    "country": "Hungary",
    "retailer": "Douglas_HU",
    "parsing_config": "./retailer_config/Douglas/douglas_parsing.json",
    "gcloud_path": "crawl_data/Hungary/Douglas_HU/",
    "department": "Perfumes",
    "category": "Perfumes",
    "page": "Perfumes",
    "page_url": "https://www.douglas.hu/c/parfumok/",
    "file_name": "Hungary_DOUGLAS_HU_PERFUME_PERFUME_PERFUME"
  },
  {
    "country": "Hungary",
    "retailer": "Douglas_HU",
    "parsing_config": "./retailer_config/Douglas/douglas_parsing.json",
    "gcloud_path": "crawl_data/Hungary/Douglas_HU/",
    "department": "Perfumes",
    "category": "Womens PERFUMES AND ACCESSORIES",
    "page": "Womens PERFUMES AND ACCESSORIES",
    "page_url": "https://www.douglas.hu/c/parfumok/noi-parfumok-es-kiegeszitok/",
    "file_name": "Hungary_DOUGLAS_HU_PERFUME_WOMEN|sq|S|sp|PERFUMES|sp|AND|sp|ACCESSORIES_WOMEN|sq|S|sp|PERFUMES|sp|AND|sp|ACCESSORIES"
  },
  {
    "country": "Hungary",
    "retailer": "Douglas_HU",
    "parsing_config": "./retailer_config/Douglas/douglas_parsing.json",
    "gcloud_path": "crawl_data/Hungary/Douglas_HU/",
    "department": "Perfumes",
    "category": "Womens PERFUMES AND ACCESSORIES",
    "page": "Womens scents",
    "page_url": "https://www.douglas.hu/c/parfumok/noi-parfumok-es-kiegeszitok/noi-illatok/",
    "file_name": "Hungary_DOUGLAS_HU_PERFUME_WOMEN|sq|S|sp|PERFUMES|sp|AND|sp|ACCESSORIES_Women|sq|s|sp|scents"
  },
  {
    "country": "Hungary",
    "retailer": "Douglas_HU",
    "parsing_config": "./retailer_config/Douglas/douglas_parsing.json",
    "gcloud_path": "crawl_data/Hungary/Douglas_HU/",
    "department": "Perfumes",
    "category": "Womens PERFUMES AND ACCESSORIES",
    "page": "Deodorants",
    "page_url": "https://www.douglas.hu/c/parfumok/noi-parfumok-es-kiegeszitok/dezodorok/",
    "file_name": "Hungary_DOUGLAS_HU_PERFUME_WOMEN|sq|S|sp|PERFUMES|sp|AND|sp|ACCESSORIES_Deodorants"
  },
  {
    "country": "Hungary",
    "retailer": "Douglas_HU",
    "parsing_config": "./retailer_config/Douglas/douglas_parsing.json",
    "gcloud_path": "crawl_data/Hungary/Douglas_HU/",
    "department": "Perfumes",
    "category": "Womens PERFUMES AND ACCESSORIES",
    "page": "Bodycare",
    "page_url": "https://www.douglas.hu/c/parfumok/noi-parfumok-es-kiegeszitok/testapolas/",
    "file_name": "Hungary_DOUGLAS_HU_PERFUME_WOMEN|sq|S|sp|PERFUMES|sp|AND|sp|ACCESSORIES_Body|sp|care"
  },
  {
    "country": "Hungary",
    "retailer": "Douglas_HU",
    "parsing_config": "./retailer_config/Douglas/douglas_parsing.json",
    "gcloud_path": "crawl_data/Hungary/Douglas_HU/",
    "department": "Perfumes",
    "category": "Womens PERFUMES AND ACCESSORIES",
    "page": "Shower gel",
    "page_url": "https://www.douglas.hu/c/parfumok/noi-parfumok-es-kiegeszitok/tusfurdo/",
    "file_name": "Hungary_DOUGLAS_HU_PERFUME_WOMEN|sq|S|sp|PERFUMES|sp|AND|sp|ACCESSORIES_Shower|sp|gel"
  },
  {
    "country": "Hungary",
    "retailer": "Douglas_HU",
    "parsing_config": "./retailer_config/Douglas/douglas_parsing.json",
    "gcloud_path": "crawl_data/Hungary/Douglas_HU/",
    "department": "Perfumes",
    "category": "Womens PERFUMES AND ACCESSORIES",
    "page": "Sets",
    "page_url": "https://www.douglas.hu/c/parfumok/noi-parfumok-es-kiegeszitok/szettek/",
    "file_name": "Hungary_DOUGLAS_HU_PERFUME_WOMEN|sq|S|sp|PERFUMES|sp|AND|sp|ACCESSORIES_Sets"
  },
  {
    "country": "Hungary",
    "retailer": "Douglas_HU",
    "parsing_config": "./retailer_config/Douglas/douglas_parsing.json",
    "gcloud_path": "crawl_data/Hungary/Douglas_HU/",
    "department": "Perfumes",
    "category": "Womens PERFUMES AND ACCESSORIES",
    "page": "Scented accessories",
    "page_url": "https://www.douglas.hu/c/parfumok/noi-parfumok-es-kiegeszitok/illatositott-kiegeszitok/",
    "file_name": "Hungary_DOUGLAS_HU_PERFUME_WOMEN|sq|S|sp|PERFUMES|sp|AND|sp|ACCESSORIES_Scented|sp|accessories"
  },
  {
    "country": "Hungary",
    "retailer": "Douglas_HU",
    "parsing_config": "./retailer_config/Douglas/douglas_parsing.json",
    "gcloud_path": "crawl_data/Hungary/Douglas_HU/",
    "department": "Perfumes",
    "category": "Womens PERFUMES AND ACCESSORIES",
    "page": "Soap",
    "page_url": "https://www.douglas.hu/c/parfumok/noi-parfumok-es-kiegeszitok/szappan/",
    "file_name": "Hungary_DOUGLAS_HU_PERFUME_WOMEN|sq|S|sp|PERFUMES|sp|AND|sp|ACCESSORIES_Soap"
  },
  {
    "country": "Hungary",
    "retailer": "Douglas_HU",
    "parsing_config": "./retailer_config/Douglas/douglas_parsing.json",
    "gcloud_path": "crawl_data/Hungary/Douglas_HU/",
    "department": "Perfumes",
    "category": "MEN'S PERFUMES AND ACCESSORIES",
    "page": "MEN'S PERFUMES AND ACCESSORIES",
    "page_url": "https://www.douglas.hu/c/parfumok/ferfi-parfumok-es-kiegeszitok/",
    "file_name": "Hungary_DOUGLAS_HU_PERFUME_MEN|sq|S|sp|PERFUMES|sp|AND|sp|ACCESSORIES_MEN|sq|S|sp|PERFUMES|sp|AND|sp|ACCESSORIES"
  },
  {
    "country": "Hungary",
    "retailer": "Douglas_HU",
    "parsing_config": "./retailer_config/Douglas/douglas_parsing.json",
    "gcloud_path": "crawl_data/Hungary/Douglas_HU/",
    "department": "Perfumes",
    "category": "MEN'S PERFUMES AND ACCESSORIES",
    "page": "Men's scents",
    "page_url": "https://www.douglas.hu/c/parfumok/ferfi-parfumok-es-kiegeszitok/ferfi-illatok/",
    "file_name": "Hungary_DOUGLAS_HU_PERFUME_MEN|sq|S|sp|PERFUMES|sp|AND|sp|ACCESSORIES_Men|sq|s|sp|scents"
  },
  {
    "country": "Hungary",
    "retailer": "Douglas_HU",
    "parsing_config": "./retailer_config/Douglas/douglas_parsing.json",
    "gcloud_path": "crawl_data/Hungary/Douglas_HU/",
    "department": "Perfumes",
    "category": "MEN'S PERFUMES AND ACCESSORIES",
    "page": "Shaving",
    "page_url": "https://www.douglas.hu/c/parfumok/ferfi-parfumok-es-kiegeszitok/borotvalkozas/",
    "file_name": "Hungary_DOUGLAS_HU_PERFUME_MEN|sq|S|sp|PERFUMES|sp|AND|sp|ACCESSORIES_Shaving"
  },
  {
    "country": "Hungary",
    "retailer": "Douglas_HU",
    "parsing_config": "./retailer_config/Douglas/douglas_parsing.json",
    "gcloud_path": "crawl_data/Hungary/Douglas_HU/",
    "department": "Perfumes",
    "category": "MEN'S PERFUMES AND ACCESSORIES",
    "page": "Shower gel, shampoo",
    "page_url": "https://www.douglas.hu/c/parfumok/ferfi-parfumok-es-kiegeszitok/tusfurdo-sampon/",
    "file_name": "Hungary_DOUGLAS_HU_PERFUME_MEN|sq|S|sp|PERFUMES|sp|AND|sp|ACCESSORIES_Shower|sp|gel,|sp|shampoo"
  },
  {
    "country": "Hungary",
    "retailer": "Douglas_HU",
    "parsing_config": "./retailer_config/Douglas/douglas_parsing.json",
    "gcloud_path": "crawl_data/Hungary/Douglas_HU/",
    "department": "Perfumes",
    "category": "MEN'S PERFUMES AND ACCESSORIES",
    "page": "Deodorants",
    "page_url": "https://www.douglas.hu/c/parfumok/ferfi-parfumok-es-kiegeszitok/dezodorok/",
    "file_name": "Hungary_DOUGLAS_HU_PERFUME_MEN|sq|S|sp|PERFUMES|sp|AND|sp|ACCESSORIES_Deodorants"
  },
  {
    "country": "Hungary",
    "retailer": "Douglas_HU",
    "parsing_config": "./retailer_config/Douglas/douglas_parsing.json",
    "gcloud_path": "crawl_data/Hungary/Douglas_HU/",
    "department": "Perfumes",
    "category": "MEN'S PERFUMES AND ACCESSORIES",
    "page": "Sets",
    "page_url": "https://www.douglas.hu/c/parfumok/ferfi-parfumok-es-kiegeszitok/szettek/",
    "file_name": "Hungary_DOUGLAS_HU_PERFUME_MEN|sq|S|sp|PERFUMES|sp|AND|sp|ACCESSORIES_Sets"
  },
  {
    "country": "Hungary",
    "retailer": "Douglas_HU",
    "parsing_config": "./retailer_config/Douglas/douglas_parsing.json",
    "gcloud_path": "crawl_data/Hungary/Douglas_HU/",
    "department": "Perfumes",
    "category": "MEN'S PERFUMES AND ACCESSORIES",
    "page": "Bodycare",
    "page_url": "https://www.douglas.hu/c/parfumok/ferfi-parfumok-es-kiegeszitok/testapolas/",
    "file_name": "Hungary_DOUGLAS_HU_PERFUME_MEN|sq|S|sp|PERFUMES|sp|AND|sp|ACCESSORIES_Body|sp|care"
  },
  {
    "country": "Hungary",
    "retailer": "Douglas_HU",
    "parsing_config": "./retailer_config/Douglas/douglas_parsing.json",
    "gcloud_path": "crawl_data/Hungary/Douglas_HU/",
    "department": "Perfumes",
    "category": "MEN'S PERFUMES AND ACCESSORIES",
    "page": "Scented accessories",
    "page_url": "https://www.douglas.hu/c/parfumok/ferfi-parfumok-es-kiegeszitok/illatositott-kiegeszitok/",
    "file_name": "Hungary_DOUGLAS_HU_PERFUME_MEN|sq|S|sp|PERFUMES|sp|AND|sp|ACCESSORIES_Scented|sp|accessories"
  },
  {
    "country": "Hungary",
    "retailer": "Douglas_HU",
    "parsing_config": "./retailer_config/Douglas/douglas_parsing.json",
    "gcloud_path": "crawl_data/Hungary/Douglas_HU/",
    "department": "Perfumes",
    "category": "MEN'S PERFUMES AND ACCESSORIES",
    "page": "Soap",
    "page_url": "https://www.douglas.hu/c/parfumok/ferfi-parfumok-es-kiegeszitok/szappan/",
    "file_name": "Hungary_DOUGLAS_HU_PERFUME_MEN|sq|S|sp|PERFUMES|sp|AND|sp|ACCESSORIES_Soap"
  },
  {
    "country": "Hungary",
    "retailer": "Douglas_HU",
    "parsing_config": "./retailer_config/Douglas/douglas_parsing.json",
    "gcloud_path": "crawl_data/Hungary/Douglas_HU/",
    "department": "Perfumes",
    "category": "UNISEX PERFUME",
    "page": "UNISEX PERFUME",
    "page_url": "https://www.douglas.hu/c/parfumok/unisex-parfum/",
    "file_name": "Hungary_DOUGLAS_HU_PERFUME_UNISEX|sp|PERFUME_UNISEX|sp|PERFUME"
  },
  {
    "country": "Hungary",
    "retailer": "Douglas_HU",
    "parsing_config": "./retailer_config/Douglas/douglas_parsing.json",
    "gcloud_path": "crawl_data/Hungary/Douglas_HU/",
    "department": "Perfumes",
    "category": "Niche Perfumes",
    "page": "Niche Perfumes",
    "page_url": "https://www.douglas.hu/c/parfumok/niche-parfum/",
    "file_name": "Hungary_DOUGLAS_HU_PERFUME_NICHE|sp|PERFUME_NICHE|sp|PERFUME"
  },
  {
    "country": "Hungary",
    "retailer": "Douglas_HU",
    "parsing_config": "./retailer_config/Douglas/douglas_parsing.json",
    "gcloud_path": "crawl_data/Hungary/Douglas_HU/",
    "department": "Care",
    "category": "Care",
    "page": "Care",
    "page_url": "https://www.douglas.hu/c/apolas/",
    "file_name": "Hungary_DOUGLAS_HU_CARE_CARE_CARE"
  },
  {
    "country": "Hungary",
    "retailer": "Douglas_HU",
    "parsing_config": "./retailer_config/Douglas/douglas_parsing.json",
    "gcloud_path": "crawl_data/Hungary/Douglas_HU/",
    "department": "Care",
    "category": "Facial Care",
    "page": "Facial Care",
    "page_url": "https://www.douglas.hu/c/apolas/arcapolas/",
    "file_name": "Hungary_DOUGLAS_HU_CARE_FACIAL|sp|CARE_FACIAL|sp|CARE"
  },
  {
    "country": "Hungary",
    "retailer": "Douglas_HU",
    "parsing_config": "./retailer_config/Douglas/douglas_parsing.json",
    "gcloud_path": "crawl_data/Hungary/Douglas_HU/",
    "department": "Care",
    "category": "Facial Care",
    "page": "Day care",
    "page_url": "https://www.douglas.hu/c/apolas/arcapolas/nappali-arcapolas/",
    "file_name": "Hungary_DOUGLAS_HU_CARE_FACIAL|sp|CARE_Day|sp|care"
  },
  {
    "country": "Hungary",
    "retailer": "Douglas_HU",
    "parsing_config": "./retailer_config/Douglas/douglas_parsing.json",
    "gcloud_path": "crawl_data/Hungary/Douglas_HU/",
    "department": "Care",
    "category": "Facial Care",
    "page": "Night care",
    "page_url": "https://www.douglas.hu/c/apolas/arcapolas/ejszakai-arcapolas/",
    "file_name": "Hungary_DOUGLAS_HU_CARE_FACIAL|sp|CARE_Night|sp|care"
  },
  {
    "country": "Hungary",
    "retailer": "Douglas_HU",
    "parsing_config": "./retailer_config/Douglas/douglas_parsing.json",
    "gcloud_path": "crawl_data/Hungary/Douglas_HU/",
    "department": "Care",
    "category": "Facial Care",
    "page": "Face Cleansing",
    "page_url": "https://www.douglas.hu/c/apolas/arcapolas/arctisztitas/",
    "file_name": "Hungary_DOUGLAS_HU_CARE_FACIAL|sp|CARE_Face|sp|cleaning"
  },
  {
    "country": "Hungary",
    "retailer": "Douglas_HU",
    "parsing_config": "./retailer_config/Douglas/douglas_parsing.json",
    "gcloud_path": "crawl_data/Hungary/Douglas_HU/",
    "department": "Care",
    "category": "Facial Care",
    "page": "Eyecare",
    "page_url": "https://www.douglas.hu/c/apolas/arcapolas/szemkornyekapolo/",
    "file_name": "Hungary_DOUGLAS_HU_CARE_FACIAL|sp|CARE_Eye|sp|care"
  },
  {
    "country": "Hungary",
    "retailer": "Douglas_HU",
    "parsing_config": "./retailer_config/Douglas/douglas_parsing.json",
    "gcloud_path": "crawl_data/Hungary/Douglas_HU/",
    "department": "Care",
    "category": "Facial Care",
    "page": "Special nurses, serums and cures",
    "page_url": "https://www.douglas.hu/c/apolas/arcapolas/specialis-apolok-szerumok-es-kurak/",
    "file_name": "Hungary_DOUGLAS_HU_CARE_FACIAL|sp|CARE_Special|sp|nurses,|sp|serums|sp|and|sp|cures"
  },
  {
    "country": "Hungary",
    "retailer": "Douglas_HU",
    "parsing_config": "./retailer_config/Douglas/douglas_parsing.json",
    "gcloud_path": "crawl_data/Hungary/Douglas_HU/",
    "department": "Care",
    "category": "Facial Care",
    "page": "Anti-aging care",
    "page_url": "https://www.douglas.hu/c/apolas/arcapolas/oregedesgatlo-apolas/",
    "file_name": "Hungary_DOUGLAS_HU_CARE_FACIAL|sp|CARE_Anti|h|aging|sp|care"
  },
  {
    "country": "Hungary",
    "retailer": "Douglas_HU",
    "parsing_config": "./retailer_config/Douglas/douglas_parsing.json",
    "gcloud_path": "crawl_data/Hungary/Douglas_HU/",
    "department": "Care",
    "category": "Facial Care",
    "page": "Maks",
    "page_url": "https://www.douglas.hu/c/apolas/arcapolas/maszkok/",
    "file_name": "Hungary_DOUGLAS_HU_CARE_FACIAL|sp|CARE_Masks"
  },
  {
    "country": "Hungary",
    "retailer": "Douglas_HU",
    "parsing_config": "./retailer_config/Douglas/douglas_parsing.json",
    "gcloud_path": "crawl_data/Hungary/Douglas_HU/",
    "department": "Care",
    "category": "Facial Care",
    "page": "Lip Care",
    "page_url": "https://www.douglas.hu/c/apolas/arcapolas/ajakapolas/",
    "file_name": "Hungary_DOUGLAS_HU_CARE_FACIAL|sp|CARE_Lip|sp|care"
  },
  {
    "country": "Hungary",
    "retailer": "Douglas_HU",
    "parsing_config": "./retailer_config/Douglas/douglas_parsing.json",
    "gcloud_path": "crawl_data/Hungary/Douglas_HU/",
    "department": "Care",
    "category": "Facial Care",
    "page": "Eyelash / eyebrow care",
    "page_url": "https://www.douglas.hu/c/apolas/arcapolas/szempillaszemoldok-apolas/",
    "file_name": "Hungary_DOUGLAS_HU_CARE_FACIAL|sp|CARE_Eyelash|sp||fs||sp|eyebrow|sp|care"
  },
  {
    "country": "Hungary",
    "retailer": "Douglas_HU",
    "parsing_config": "./retailer_config/Douglas/douglas_parsing.json",
    "gcloud_path": "crawl_data/Hungary/Douglas_HU/",
    "department": "Care",
    "category": "Facial Care",
    "page": "Sets",
    "page_url": "https://www.douglas.hu/c/apolas/arcapolas/szettek/",
    "file_name": "Hungary_DOUGLAS_HU_CARE_FACIAL|sp|CARE_Sets"
  },
  {
    "country": "Hungary",
    "retailer": "Douglas_HU",
    "parsing_config": "./retailer_config/Douglas/douglas_parsing.json",
    "gcloud_path": "crawl_data/Hungary/Douglas_HU/",
    "department": "Care",
    "category": "Facial Care",
    "page": "Accessories",
    "page_url": "https://www.douglas.hu/c/apolas/arcapolas/kiegeszitok/",
    "file_name": "Hungary_DOUGLAS_HU_CARE_FACIAL|sp|CARE_Accessories"
  },
  {
    "country": "Hungary",
    "retailer": "Douglas_HU",
    "parsing_config": "./retailer_config/Douglas/douglas_parsing.json",
    "gcloud_path": "crawl_data/Hungary/Douglas_HU/",
    "department": "Care",
    "category": "Facial Care",
    "page": "All categories",
    "page_url": "https://www.douglas.hu/c/apolas/arcapolas/",
    "file_name": "Hungary_DOUGLAS_HU_CARE_FACIAL|sp|CARE_All|sp|categories"
  },
  {
    "country": "Hungary",
    "retailer": "Douglas_HU",
    "parsing_config": "./retailer_config/Douglas/douglas_parsing.json",
    "gcloud_path": "crawl_data/Hungary/Douglas_HU/",
    "department": "Care",
    "category": "Bodycare",
    "page": "Bodycare",
    "page_url": "https://www.douglas.hu/c/apolas/testapolas/",
    "file_name": "Hungary_DOUGLAS_HU_CARE_BODY|sp|CARE_BODY|sp|CARE"
  },
  {
    "country": "Hungary",
    "retailer": "Douglas_HU",
    "parsing_config": "./retailer_config/Douglas/douglas_parsing.json",
    "gcloud_path": "crawl_data/Hungary/Douglas_HU/",
    "department": "Care",
    "category": "Bodycare",
    "page": "Care",
    "page_url": "https://www.douglas.hu/c/apolas/testapolas/apolas/",
    "file_name": "Hungary_DOUGLAS_HU_CARE_BODY|sp|CARE_Care"
  },
  {
    "country": "Hungary",
    "retailer": "Douglas_HU",
    "parsing_config": "./retailer_config/Douglas/douglas_parsing.json",
    "gcloud_path": "crawl_data/Hungary/Douglas_HU/",
    "department": "Care",
    "category": "Bodycare",
    "page": "Shower gels, cleaners",
    "page_url": "https://www.douglas.hu/c/apolas/testapolas/tusfurdok-tisztitok/",
    "file_name": "Hungary_DOUGLAS_HU_CARE_BODY|sp|CARE_Shower|sp|gels,|sp|cleaners"
  },
  {
    "country": "Hungary",
    "retailer": "Douglas_HU",
    "parsing_config": "./retailer_config/Douglas/douglas_parsing.json",
    "gcloud_path": "crawl_data/Hungary/Douglas_HU/",
    "department": "Care",
    "category": "Bodycare",
    "page": "Deodorants",
    "page_url": "https://www.douglas.hu/c/apolas/testapolas/dezodorok/",
    "file_name": "Hungary_DOUGLAS_HU_CARE_BODY|sp|CARE_Deodorants"
  },
  {
    "country": "Hungary",
    "retailer": "Douglas_HU",
    "parsing_config": "./retailer_config/Douglas/douglas_parsing.json",
    "gcloud_path": "crawl_data/Hungary/Douglas_HU/",
    "department": "Care",
    "category": "Bodycare",
    "page": "Baby Care",
    "page_url": "https://www.douglas.hu/c/apolas/testapolas/baba-apolas/",
    "file_name": "Hungary_DOUGLAS_HU_CARE_BODY|sp|CARE_Baby|sp|care"
  },
  {
    "country": "Hungary",
    "retailer": "Douglas_HU",
    "parsing_config": "./retailer_config/Douglas/douglas_parsing.json",
    "gcloud_path": "crawl_data/Hungary/Douglas_HU/",
    "department": "Care",
    "category": "Bodycare",
    "page": "Sets",
    "page_url": "https://www.douglas.hu/c/apolas/testapolas/szettek/",
    "file_name": "Hungary_DOUGLAS_HU_CARE_BODY|sp|CARE_Sets"
  },
  {
    "country": "Hungary",
    "retailer": "Douglas_HU",
    "parsing_config": "./retailer_config/Douglas/douglas_parsing.json",
    "gcloud_path": "crawl_data/Hungary/Douglas_HU/",
    "department": "Care",
    "category": "Bodycare",
    "page": "Anti-cellulite / Slimming creams, firming",
    "page_url": "https://www.douglas.hu/c/apolas/testapolas/cellulitisz-elleni-karcsusito-kremek-feszesitok/",
    "file_name": "Hungary_DOUGLAS_HU_CARE_BODY|sp|CARE_Anti|h|cellulite|sp||fs||sp|Slimming|sp|creams,|sp|firming"
  },
  {
    "country": "Hungary",
    "retailer": "Douglas_HU",
    "parsing_config": "./retailer_config/Douglas/douglas_parsing.json",
    "gcloud_path": "crawl_data/Hungary/Douglas_HU/",
    "department": "Care",
    "category": "Bodycare",
    "page": "Accessories",
    "page_url": "https://www.douglas.hu/c/apolas/testapolas/kiegeszitok/",
    "file_name": "Hungary_DOUGLAS_HU_CARE_BODY|sp|CARE_Accessories"
  },
  {
    "country": "Hungary",
    "retailer": "Douglas_HU",
    "parsing_config": "./retailer_config/Douglas/douglas_parsing.json",
    "gcloud_path": "crawl_data/Hungary/Douglas_HU/",
    "department": "Care",
    "category": "HAND AND FOOT CARE",
    "page": "HAND AND FOOT CARE",
    "page_url": "https://www.douglas.hu/c/apolas/kez-es-labapolas/",
    "file_name": "Hungary_DOUGLAS_HU_CARE_HAND|sp|AND|sp|FOOT|sp|CARE_HAND|sp|AND|sp|FOOT|sp|CARE"
  },
  {
    "country": "Hungary",
    "retailer": "Douglas_HU",
    "parsing_config": "./retailer_config/Douglas/douglas_parsing.json",
    "gcloud_path": "crawl_data/Hungary/Douglas_HU/",
    "department": "Care",
    "category": "HAND AND FOOT CARE",
    "page": "Hand disinfection, cleaning",
    "page_url": "https://www.douglas.hu/c/apolas/kez-es-labapolas/kezfertotlenites-tisztitas/",
    "file_name": "Hungary_DOUGLAS_HU_CARE_HAND|sp|AND|sp|FOOT|sp|CARE_Hand|sp|disinfection,|sp|cleaning"
  },
  {
    "country": "Hungary",
    "retailer": "Douglas_HU",
    "parsing_config": "./retailer_config/Douglas/douglas_parsing.json",
    "gcloud_path": "crawl_data/Hungary/Douglas_HU/",
    "department": "Care",
    "category": "HAND AND FOOT CARE",
    "page": "Handcare",
    "page_url": "https://www.douglas.hu/c/apolas/kez-es-labapolas/kezapolas/",
    "file_name": "Hungary_DOUGLAS_HU_CARE_HAND|sp|AND|sp|FOOT|sp|CARE_Hand|sp|care"
  },
  {
    "country": "Hungary",
    "retailer": "Douglas_HU",
    "parsing_config": "./retailer_config/Douglas/douglas_parsing.json",
    "gcloud_path": "crawl_data/Hungary/Douglas_HU/",
    "department": "Care",
    "category": "HAND AND FOOT CARE",
    "page": "Footcare",
    "page_url": "https://www.douglas.hu/c/apolas/kez-es-labapolas/labapolas/",
    "file_name": "Hungary_DOUGLAS_HU_CARE_HAND|sp|AND|sp|FOOT|sp|CARE_Foot|sp|care"
  },
  {
    "country": "Hungary",
    "retailer": "Douglas_HU",
    "parsing_config": "./retailer_config/Douglas/douglas_parsing.json",
    "gcloud_path": "crawl_data/Hungary/Douglas_HU/",
    "department": "Care",
    "category": "HAND AND FOOT CARE",
    "page": "Accessories",
    "page_url": "https://www.douglas.hu/c/apolas/kez-es-labapolas/kiegeszitok/",
    "file_name": "Hungary_DOUGLAS_HU_CARE_HAND|sp|AND|sp|FOOT|sp|CARE_Accessories"
  },
  {
    "country": "Hungary",
    "retailer": "Douglas_HU",
    "parsing_config": "./retailer_config/Douglas/douglas_parsing.json",
    "gcloud_path": "crawl_data/Hungary/Douglas_HU/",
    "department": "Care",
    "category": "HAND AND FOOT CARE",
    "page": "Sets",
    "page_url": "https://www.douglas.hu/c/apolas/kez-es-labapolas/szettek/",
    "file_name": "Hungary_DOUGLAS_HU_CARE_HAND|sp|AND|sp|FOOT|sp|CARE_Sets"
  },
  {
    "country": "Hungary",
    "retailer": "Douglas_HU",
    "parsing_config": "./retailer_config/Douglas/douglas_parsing.json",
    "gcloud_path": "crawl_data/Hungary/Douglas_HU/",
    "department": "Care",
    "category": "Sun Bathing",
    "page": "Sun Bathing",
    "page_url": "https://www.douglas.hu/c/apolas/napozok/",
    "file_name": "Hungary_DOUGLAS_HU_CARE_SUNBATHING_SUNBATHING"
  },
  {
    "country": "Hungary",
    "retailer": "Douglas_HU",
    "parsing_config": "./retailer_config/Douglas/douglas_parsing.json",
    "gcloud_path": "crawl_data/Hungary/Douglas_HU/",
    "department": "Care",
    "category": "Sun Bathing",
    "page": "Aftersun",
    "page_url": "https://www.douglas.hu/c/apolas/napozok/aftersun/",
    "file_name": "Hungary_DOUGLAS_HU_CARE_SUNBATHING_Aftersun"
  },
  {
    "country": "Hungary",
    "retailer": "Douglas_HU",
    "parsing_config": "./retailer_config/Douglas/douglas_parsing.json",
    "gcloud_path": "crawl_data/Hungary/Douglas_HU/",
    "department": "Care",
    "category": "Sun Bathing",
    "page": "Sunscreens for the face",
    "page_url": "https://www.douglas.hu/c/apolas/napozok/fenyvedok-arcra/",
    "file_name": "Hungary_DOUGLAS_HU_CARE_SUNBATHING_Sunscreens|sp|for|sp|the|sp|face"
  },
  {
    "country": "Hungary",
    "retailer": "Douglas_HU",
    "parsing_config": "./retailer_config/Douglas/douglas_parsing.json",
    "gcloud_path": "crawl_data/Hungary/Douglas_HU/",
    "department": "Care",
    "category": "Sun Bathing",
    "page": "Self tanning",
    "page_url": "https://www.douglas.hu/c/apolas/napozok/onbarnito/",
    "file_name": "Hungary_DOUGLAS_HU_CARE_SUNBATHING_Self|sp|tanning"
  },
  {
    "country": "Hungary",
    "retailer": "Douglas_HU",
    "parsing_config": "./retailer_config/Douglas/douglas_parsing.json",
    "gcloud_path": "crawl_data/Hungary/Douglas_HU/",
    "department": "Care",
    "category": "Sun Bathing",
    "page": "Sun Bathing",
    "page_url": "https://www.douglas.hu/c/apolas/napozok/napozok/",
    "file_name": "Hungary_DOUGLAS_HU_CARE_SUNBATHING_Sunbathing"
  },
  {
    "country": "Hungary",
    "retailer": "Douglas_HU",
    "parsing_config": "./retailer_config/Douglas/douglas_parsing.json",
    "gcloud_path": "crawl_data/Hungary/Douglas_HU/",
    "department": "Care",
    "category": "Sun Bathing",
    "page": "Sets",
    "page_url": "https://www.douglas.hu/c/apolas/napozok/szettek/",
    "file_name": "Hungary_DOUGLAS_HU_CARE_SUNBATHING_Sets"
  },
  {
    "country": "Hungary",
    "retailer": "Douglas_HU",
    "parsing_config": "./retailer_config/Douglas/douglas_parsing.json",
    "gcloud_path": "crawl_data/Hungary/Douglas_HU/",
    "department": "Care",
    "category": "Mens Grooming",
    "page": "MEN'S GROOMING",
    "page_url": "https://www.douglas.hu/c/apolas/ferfi-apolas/",
    "file_name": "Hungary_DOUGLAS_HU_CARE_MEN|sq|S|sp|GROOMING_MEN|sq|S|sp|GROOMING"
  },
  {
    "country": "Hungary",
    "retailer": "Douglas_HU",
    "parsing_config": "./retailer_config/Douglas/douglas_parsing.json",
    "gcloud_path": "crawl_data/Hungary/Douglas_HU/",
    "department": "Care",
    "category": "Mens Grooming",
    "page": "Men's facial care",
    "page_url": "https://www.douglas.hu/c/apolas/ferfi-apolas/ferfi-arcapolas/",
    "file_name": "Hungary_DOUGLAS_HU_CARE_MEN|sq|S|sp|GROOMING_Men|sq|s|sp|facial|sp|care"
  },
  {
    "country": "Hungary",
    "retailer": "Douglas_HU",
    "parsing_config": "./retailer_config/Douglas/douglas_parsing.json",
    "gcloud_path": "crawl_data/Hungary/Douglas_HU/",
    "department": "Care",
    "category": "Mens Grooming",
    "page": "Shaving",
    "page_url": "https://www.douglas.hu/c/apolas/ferfi-apolas/borotvalkozas/",
    "file_name": "Hungary_DOUGLAS_HU_CARE_MEN|sq|S|sp|GROOMING_Shaving"
  },
  {
    "country": "Hungary",
    "retailer": "Douglas_HU",
    "parsing_config": "./retailer_config/Douglas/douglas_parsing.json",
    "gcloud_path": "crawl_data/Hungary/Douglas_HU/",
    "department": "Care",
    "category": "Mens Grooming",
    "page": "Mens Bodycare",
    "page_url": "https://www.douglas.hu/c/apolas/ferfi-apolas/ferfi-testapolas/",
    "file_name": "Hungary_DOUGLAS_HU_CARE_MEN|sq|S|sp|GROOMING_Men|sq|s|sp|body|sp|care"
  },
  {
    "country": "Hungary",
    "retailer": "Douglas_HU",
    "parsing_config": "./retailer_config/Douglas/douglas_parsing.json",
    "gcloud_path": "crawl_data/Hungary/Douglas_HU/",
    "department": "Care",
    "category": "Mens Grooming",
    "page": "Deodorants",
    "page_url": "https://www.douglas.hu/c/apolas/ferfi-apolas/dezodorok/",
    "file_name": "Hungary_DOUGLAS_HU_CARE_MEN|sq|S|sp|GROOMING_Deodorants"
  },
  {
    "country": "Hungary",
    "retailer": "Douglas_HU",
    "parsing_config": "./retailer_config/Douglas/douglas_parsing.json",
    "gcloud_path": "crawl_data/Hungary/Douglas_HU/",
    "department": "Care",
    "category": "Mens Grooming",
    "page": "Shower gels, shampoos",
    "page_url": "https://www.douglas.hu/c/apolas/ferfi-apolas/tusfurdok-samponok/",
    "file_name": "Hungary_DOUGLAS_HU_CARE_MEN|sq|S|sp|GROOMING_Shower|sp|gels,|sp|shampoos"
  },
  {
    "country": "Hungary",
    "retailer": "Douglas_HU",
    "parsing_config": "./retailer_config/Douglas/douglas_parsing.json",
    "gcloud_path": "crawl_data/Hungary/Douglas_HU/",
    "department": "Care",
    "category": "Mens Grooming",
    "page": "Sets",
    "page_url": "https://www.douglas.hu/c/apolas/ferfi-apolas/szettek/",
    "file_name": "Hungary_DOUGLAS_HU_CARE_MEN|sq|S|sp|GROOMING_Sets"
  },
  {
    "country": "Hungary",
    "retailer": "Douglas_HU",
    "parsing_config": "./retailer_config/Douglas/douglas_parsing.json",
    "gcloud_path": "crawl_data/Hungary/Douglas_HU/",
    "department": "Care",
    "category": "PROFESSIONAL BEAUTY TOOLS",
    "page": "PROFESSIONAL BEAUTY TOOLS",
    "page_url": "https://www.douglas.hu/c/apolas/professzionalis-szepsegapolasi-eszkozok/",
    "file_name": "Hungary_DOUGLAS_HU_CARE_PROFESSIONAL|sp|BEAUTY|sp|TOOLS_PROFESSIONAL|sp|BEAUTY|sp|TOOLS"
  },
  {
    "country": "Hungary",
    "retailer": "Douglas_HU",
    "parsing_config": "./retailer_config/Douglas/douglas_parsing.json",
    "gcloud_path": "crawl_data/Hungary/Douglas_HU/",
    "department": "Care",
    "category": "PROFESSIONAL BEAUTY TOOLS",
    "page": "Face Cleansing",
    "page_url": "https://www.douglas.hu/c/apolas/professzionalis-szepsegapolasi-eszkozok/arctisztitas/",
    "file_name": "Hungary_DOUGLAS_HU_CARE_PROFESSIONAL|sp|BEAUTY|sp|TOOLS_Face|sp|cleaning"
  },
  {
    "country": "Hungary",
    "retailer": "Douglas_HU",
    "parsing_config": "./retailer_config/Douglas/douglas_parsing.json",
    "gcloud_path": "crawl_data/Hungary/Douglas_HU/",
    "department": "Care",
    "category": "PROFESSIONAL BEAUTY TOOLS",
    "page": "Anti-aging",
    "page_url": "https://www.douglas.hu/c/apolas/professzionalis-szepsegapolasi-eszkozok/oregedesgatlo/",
    "file_name": "Hungary_DOUGLAS_HU_CARE_PROFESSIONAL|sp|BEAUTY|sp|TOOLS_Anti|h|aging"
  },
  {
    "country": "Hungary",
    "retailer": "Douglas_HU",
    "parsing_config": "./retailer_config/Douglas/douglas_parsing.json",
    "gcloud_path": "crawl_data/Hungary/Douglas_HU/",
    "department": "Care",
    "category": "PROFESSIONAL BEAUTY TOOLS",
    "page": "Hair Removal",
    "page_url": "https://www.douglas.hu/c/apolas/professzionalis-szepsegapolasi-eszkozok/szortelenites/",
    "file_name": "Hungary_DOUGLAS_HU_CARE_PROFESSIONAL|sp|BEAUTY|sp|TOOLS_Hair|sp|removal"
  },
  {
    "country": "Hungary",
    "retailer": "Douglas_HU",
    "parsing_config": "./retailer_config/Douglas/douglas_parsing.json",
    "gcloud_path": "crawl_data/Hungary/Douglas_HU/",
    "department": "Care",
    "category": "Dental Care",
    "page": "Dental Care",
    "page_url": "https://www.douglas.hu/c/apolas/fogapolas/",
    "file_name": "Hungary_DOUGLAS_HU_CARE_DENTAL|sp|CARE_DENTAL|sp|CARE"
  },
  {
    "country": "Hungary",
    "retailer": "Douglas_HU",
    "parsing_config": "./retailer_config/Douglas/douglas_parsing.json",
    "gcloud_path": "crawl_data/Hungary/Douglas_HU/",
    "department": "Care",
    "category": "Dental Care",
    "page": "Electric toothbrushes",
    "page_url": "https://www.douglas.hu/c/apolas/fogapolas/elektromos-fogkefek/",
    "file_name": "Hungary_DOUGLAS_HU_CARE_DENTAL|sp|CARE_Electric|sp|toothbrushes"
  },
  {
    "country": "Hungary",
    "retailer": "Douglas_HU",
    "parsing_config": "./retailer_config/Douglas/douglas_parsing.json",
    "gcloud_path": "crawl_data/Hungary/Douglas_HU/",
    "department": "Care",
    "category": "Dental Care",
    "page": "Toothpastes, mouthwashes",
    "page_url": "https://www.douglas.hu/c/apolas/fogapolas/fogkremek-szajvizek/",
    "file_name": "Hungary_DOUGLAS_HU_CARE_DENTAL|sp|CARE_Toothpastes,|sp|mouthwashes"
  },
  {
    "country": "Hungary",
    "retailer": "Douglas_HU",
    "parsing_config": "./retailer_config/Douglas/douglas_parsing.json",
    "gcloud_path": "crawl_data/Hungary/Douglas_HU/",
    "department": "Make Up",
    "category": "Make Up",
    "page": "MAKEUP",
    "page_url": "https://www.douglas.hu/c/smink/",
    "file_name": "Hungary_DOUGLAS_HU_MAKEUP_MAKEUP_MAKEUP"
  },
  {
    "country": "Hungary",
    "retailer": "Douglas_HU",
    "parsing_config": "./retailer_config/Douglas/douglas_parsing.json",
    "gcloud_path": "crawl_data/Hungary/Douglas_HU/",
    "department": "Make Up",
    "category": "ARC",
    "page": "ARC",
    "page_url": "https://www.douglas.hu/c/smink/arc/",
    "file_name": "Hungary_DOUGLAS_HU_MAKEUP_ARC_ARC"
  },
  {
    "country": "Hungary",
    "retailer": "Douglas_HU",
    "parsing_config": "./retailer_config/Douglas/douglas_parsing.json",
    "gcloud_path": "crawl_data/Hungary/Douglas_HU/",
    "department": "Make Up",
    "category": "ARC",
    "page": "Foundation",
    "page_url": "https://www.douglas.hu/c/smink/arc/alapozo/",
    "file_name": "Hungary_DOUGLAS_HU_MAKEUP_ARC_Foundation"
  },
  {
    "country": "Hungary",
    "retailer": "Douglas_HU",
    "parsing_config": "./retailer_config/Douglas/douglas_parsing.json",
    "gcloud_path": "crawl_data/Hungary/Douglas_HU/",
    "department": "Make Up",
    "category": "ARC",
    "page": "Blush",
    "page_url": "https://www.douglas.hu/c/smink/arc/pirosito/",
    "file_name": "Hungary_DOUGLAS_HU_MAKEUP_ARC_Blush"
  },
  {
    "country": "Hungary",
    "retailer": "Douglas_HU",
    "parsing_config": "./retailer_config/Douglas/douglas_parsing.json",
    "gcloud_path": "crawl_data/Hungary/Douglas_HU/",
    "department": "Make Up",
    "category": "ARC",
    "page": "Bronze",
    "page_url": "https://www.douglas.hu/c/smink/arc/bronzosito/",
    "file_name": "Hungary_DOUGLAS_HU_MAKEUP_ARC_Bronze"
  },
  {
    "country": "Hungary",
    "retailer": "Douglas_HU",
    "parsing_config": "./retailer_config/Douglas/douglas_parsing.json",
    "gcloud_path": "crawl_data/Hungary/Douglas_HU/",
    "department": "Make Up",
    "category": "ARC",
    "page": "Powder",
    "page_url": "https://www.douglas.hu/c/smink/arc/puder/",
    "file_name": "Hungary_DOUGLAS_HU_MAKEUP_ARC_Powder"
  },
  {
    "country": "Hungary",
    "retailer": "Douglas_HU",
    "parsing_config": "./retailer_config/Douglas/douglas_parsing.json",
    "gcloud_path": "crawl_data/Hungary/Douglas_HU/",
    "department": "Make Up",
    "category": "ARC",
    "page": "Highlighter",
    "page_url": "https://www.douglas.hu/c/smink/arc/highlighter/",
    "file_name": "Hungary_DOUGLAS_HU_MAKEUP_ARC_Highlighter"
  },
  {
    "country": "Hungary",
    "retailer": "Douglas_HU",
    "parsing_config": "./retailer_config/Douglas/douglas_parsing.json",
    "gcloud_path": "crawl_data/Hungary/Douglas_HU/",
    "department": "Make Up",
    "category": "ARC",
    "page": "reviser",
    "page_url": "https://www.douglas.hu/c/smink/arc/korrektor/",
    "file_name": "Hungary_DOUGLAS_HU_MAKEUP_ARC_reviser"
  },
  {
    "country": "Hungary",
    "retailer": "Douglas_HU",
    "parsing_config": "./retailer_config/Douglas/douglas_parsing.json",
    "gcloud_path": "crawl_data/Hungary/Douglas_HU/",
    "department": "Make Up",
    "category": "ARC",
    "page": "Fixer",
    "page_url": "https://www.douglas.hu/c/smink/arc/fixalo/",
    "file_name": "Hungary_DOUGLAS_HU_MAKEUP_ARC_Fixer"
  },
  {
    "country": "Hungary",
    "retailer": "Douglas_HU",
    "parsing_config": "./retailer_config/Douglas/douglas_parsing.json",
    "gcloud_path": "crawl_data/Hungary/Douglas_HU/",
    "department": "Make Up",
    "category": "ARC",
    "page": "Makeup kit",
    "page_url": "https://www.douglas.hu/c/smink/arc/smink-keszlet/",
    "file_name": "Hungary_DOUGLAS_HU_MAKEUP_ARC_Makeup|sp|kit"
  },
  {
    "country": "Hungary",
    "retailer": "Douglas_HU",
    "parsing_config": "./retailer_config/Douglas/douglas_parsing.json",
    "gcloud_path": "crawl_data/Hungary/Douglas_HU/",
    "department": "Make Up",
    "category": "ARC",
    "page": "Primer",
    "page_url": "https://www.douglas.hu/c/smink/arc/primer/",
    "file_name": "Hungary_DOUGLAS_HU_MAKEUP_ARC_Primer"
  },
  {
    "country": "Hungary",
    "retailer": "Douglas_HU",
    "parsing_config": "./retailer_config/Douglas/douglas_parsing.json",
    "gcloud_path": "crawl_data/Hungary/Douglas_HU/",
    "department": "Make Up",
    "category": "ARC",
    "page": "Contouring palette, pin",
    "page_url": "https://www.douglas.hu/c/smink/arc/konturozo-paletta-stift/",
    "file_name": "Hungary_DOUGLAS_HU_MAKEUP_ARC_Contouring|sp|palette,|sp|pin"
  },
  {
    "country": "Hungary",
    "retailer": "Douglas_HU",
    "parsing_config": "./retailer_config/Douglas/douglas_parsing.json",
    "gcloud_path": "crawl_data/Hungary/Douglas_HU/",
    "department": "Make Up",
    "category": "ARC",
    "page": "Makeup with light protection",
    "page_url": "https://www.douglas.hu/c/smink/arc/sminkek-fenyvedelemmel/",
    "file_name": "Hungary_DOUGLAS_HU_MAKEUP_ARC_Makeup|sp|with|sp|light|sp|protection"
  },
  {
    "country": "Hungary",
    "retailer": "Douglas_HU",
    "parsing_config": "./retailer_config/Douglas/douglas_parsing.json",
    "gcloud_path": "crawl_data/Hungary/Douglas_HU/",
    "department": "Make Up",
    "category": "ARC",
    "page": "All categories",
    "page_url": "https://www.douglas.hu/c/smink/arc/",
    "file_name": "Hungary_DOUGLAS_HU_MAKEUP_ARC_All|sp|categories"
  },
  {
    "country": "Hungary",
    "retailer": "Douglas_HU",
    "parsing_config": "./retailer_config/Douglas/douglas_parsing.json",
    "gcloud_path": "crawl_data/Hungary/Douglas_HU/",
    "department": "Make Up",
    "category": "Eyes",
    "page": "EYE",
    "page_url": "https://www.douglas.hu/c/smink/szem/",
    "file_name": "Hungary_DOUGLAS_HU_MAKEUP_EYE_EYE"
  },
  {
    "country": "Hungary",
    "retailer": "Douglas_HU",
    "parsing_config": "./retailer_config/Douglas/douglas_parsing.json",
    "gcloud_path": "crawl_data/Hungary/Douglas_HU/",
    "department": "Make Up",
    "category": "Eyes",
    "page": "Eyeshadow",
    "page_url": "https://www.douglas.hu/c/smink/szem/szemhejfestek/",
    "file_name": "Hungary_DOUGLAS_HU_MAKEUP_EYE_Eyeshadow"
  },
  {
    "country": "Hungary",
    "retailer": "Douglas_HU",
    "parsing_config": "./retailer_config/Douglas/douglas_parsing.json",
    "gcloud_path": "crawl_data/Hungary/Douglas_HU/",
    "department": "Make Up",
    "category": "Eyes",
    "page": "Mascara",
    "page_url": "https://www.douglas.hu/c/smink/szem/szempillaspiral/",
    "file_name": "Hungary_DOUGLAS_HU_MAKEUP_EYE_Mascara"
  },
  {
    "country": "Hungary",
    "retailer": "Douglas_HU",
    "parsing_config": "./retailer_config/Douglas/douglas_parsing.json",
    "gcloud_path": "crawl_data/Hungary/Douglas_HU/",
    "department": "Make Up",
    "category": "Eyes",
    "page": "Eyeliner, eyelid",
    "page_url": "https://www.douglas.hu/c/smink/szem/szemceruza-szemhejtus/",
    "file_name": "Hungary_DOUGLAS_HU_MAKEUP_EYE_Eyeliner,|sp|eyelid"
  },
  {
    "country": "Hungary",
    "retailer": "Douglas_HU",
    "parsing_config": "./retailer_config/Douglas/douglas_parsing.json",
    "gcloud_path": "crawl_data/Hungary/Douglas_HU/",
    "department": "Make Up",
    "category": "Eyes",
    "page": "Eyebrows",
    "page_url": "https://www.douglas.hu/c/smink/szem/szemoldok/",
    "file_name": "Hungary_DOUGLAS_HU_MAKEUP_EYE_Eyebrow"
  },
  {
    "country": "Hungary",
    "retailer": "Douglas_HU",
    "parsing_config": "./retailer_config/Douglas/douglas_parsing.json",
    "gcloud_path": "crawl_data/Hungary/Douglas_HU/",
    "department": "Make Up",
    "category": "Eyes",
    "page": "Sets, pallets",
    "page_url": "https://www.douglas.hu/c/smink/szem/szettek-palettak/",
    "file_name": "Hungary_DOUGLAS_HU_MAKEUP_EYE_Sets,|sp|pallets"
  },
  {
    "country": "Hungary",
    "retailer": "Douglas_HU",
    "parsing_config": "./retailer_config/Douglas/douglas_parsing.json",
    "gcloud_path": "crawl_data/Hungary/Douglas_HU/",
    "department": "Make Up",
    "category": "Eyes",
    "page": "Eyeshadow base",
    "page_url": "https://www.douglas.hu/c/smink/szem/szemhejfestek-bazis/",
    "file_name": "Hungary_DOUGLAS_HU_MAKEUP_EYE_Eyeshadow|sp|base"
  },
  {
    "country": "Hungary",
    "retailer": "Douglas_HU",
    "parsing_config": "./retailer_config/Douglas/douglas_parsing.json",
    "gcloud_path": "crawl_data/Hungary/Douglas_HU/",
    "department": "Make Up",
    "category": "Eyes",
    "page": "False eyelashes",
    "page_url": "https://www.douglas.hu/c/smink/szem/muszempillak/",
    "file_name": "Hungary_DOUGLAS_HU_MAKEUP_EYE_False|sp|eyelashes"
  },
  {
    "country": "Hungary",
    "retailer": "Douglas_HU",
    "parsing_config": "./retailer_config/Douglas/douglas_parsing.json",
    "gcloud_path": "crawl_data/Hungary/Douglas_HU/",
    "department": "Make Up",
    "category": "Eyes",
    "page": "Eyeshadow remover",
    "page_url": "https://www.douglas.hu/c/smink/szem/szemfesteklemoso/",
    "file_name": "Hungary_DOUGLAS_HU_MAKEUP_EYE_Eyeshadow|sp|remover"
  },
  {
    "country": "Hungary",
    "retailer": "Douglas_HU",
    "parsing_config": "./retailer_config/Douglas/douglas_parsing.json",
    "gcloud_path": "crawl_data/Hungary/Douglas_HU/",
    "department": "Make Up",
    "category": "INVITE",
    "page": "INVITE",
    "page_url": "https://www.douglas.hu/c/smink/ajak/",
    "file_name": "Hungary_DOUGLAS_HU_MAKEUP_INVITE_INVITE"
  },
  {
    "country": "Hungary",
    "retailer": "Douglas_HU",
    "parsing_config": "./retailer_config/Douglas/douglas_parsing.json",
    "gcloud_path": "crawl_data/Hungary/Douglas_HU/",
    "department": "Make Up",
    "category": "INVITE",
    "page": "Lipstick",
    "page_url": "https://www.douglas.hu/c/smink/ajak/ruzs/",
    "file_name": "Hungary_DOUGLAS_HU_MAKEUP_INVITE_Lipstick"
  },
  {
    "country": "Hungary",
    "retailer": "Douglas_HU",
    "parsing_config": "./retailer_config/Douglas/douglas_parsing.json",
    "gcloud_path": "crawl_data/Hungary/Douglas_HU/",
    "department": "Make Up",
    "category": "INVITE",
    "page": "Lip gloss",
    "page_url": "https://www.douglas.hu/c/smink/ajak/szajfeny/",
    "file_name": "Hungary_DOUGLAS_HU_MAKEUP_INVITE_Lip|sp|gloss"
  },
  {
    "country": "Hungary",
    "retailer": "Douglas_HU",
    "parsing_config": "./retailer_config/Douglas/douglas_parsing.json",
    "gcloud_path": "crawl_data/Hungary/Douglas_HU/",
    "department": "Make Up",
    "category": "INVITE",
    "page": "Lip balm",
    "page_url": "https://www.douglas.hu/c/smink/ajak/ajakbalzsam/",
    "file_name": "Hungary_DOUGLAS_HU_MAKEUP_INVITE_Lip|sp|balm"
  },
  {
    "country": "Hungary",
    "retailer": "Douglas_HU",
    "parsing_config": "./retailer_config/Douglas/douglas_parsing.json",
    "gcloud_path": "crawl_data/Hungary/Douglas_HU/",
    "department": "Make Up",
    "category": "INVITE",
    "page": "Lip liner",
    "page_url": "https://www.douglas.hu/c/smink/ajak/szajkonturceruza/",
    "file_name": "Hungary_DOUGLAS_HU_MAKEUP_INVITE_Lip|sp|liner"
  },
  {
    "country": "Hungary",
    "retailer": "Douglas_HU",
    "parsing_config": "./retailer_config/Douglas/douglas_parsing.json",
    "gcloud_path": "crawl_data/Hungary/Douglas_HU/",
    "department": "Make Up",
    "category": "INVITE",
    "page": "Sets",
    "page_url": "https://www.douglas.hu/c/smink/ajak/szettek/",
    "file_name": "Hungary_DOUGLAS_HU_MAKEUP_INVITE_Sets"
  },
  {
    "country": "Hungary",
    "retailer": "Douglas_HU",
    "parsing_config": "./retailer_config/Douglas/douglas_parsing.json",
    "gcloud_path": "crawl_data/Hungary/Douglas_HU/",
    "department": "Make Up",
    "category": "NAIL",
    "page": "NAIL",
    "page_url": "https://www.douglas.hu/c/smink/korom/",
    "file_name": "Hungary_DOUGLAS_HU_MAKEUP_NAIL_NAIL"
  },
  {
    "country": "Hungary",
    "retailer": "Douglas_HU",
    "parsing_config": "./retailer_config/Douglas/douglas_parsing.json",
    "gcloud_path": "crawl_data/Hungary/Douglas_HU/",
    "department": "Make Up",
    "category": "NAIL",
    "page": "Nail Polish",
    "page_url": "https://www.douglas.hu/c/smink/korom/koromlakk/",
    "file_name": "Hungary_DOUGLAS_HU_MAKEUP_NAIL_Nail|sp|polish"
  },
  {
    "country": "Hungary",
    "retailer": "Douglas_HU",
    "parsing_config": "./retailer_config/Douglas/douglas_parsing.json",
    "gcloud_path": "crawl_data/Hungary/Douglas_HU/",
    "department": "Make Up",
    "category": "NAIL",
    "page": "Nail care, cleansers, bases",
    "page_url": "https://www.douglas.hu/c/smink/korom/koromapolok-lemosok-bazisok/",
    "file_name": "Hungary_DOUGLAS_HU_MAKEUP_NAIL_Nail|sp|care,|sp|cleansers,|sp|bases"
  },
  {
    "country": "Hungary",
    "retailer": "Douglas_HU",
    "parsing_config": "./retailer_config/Douglas/douglas_parsing.json",
    "gcloud_path": "crawl_data/Hungary/Douglas_HU/",
    "department": "Make Up",
    "category": "NAIL",
    "page": "Nail design",
    "page_url": "https://www.douglas.hu/c/smink/korom/koromdesign/",
    "file_name": "Hungary_DOUGLAS_HU_MAKEUP_NAIL_Nail|sp|design"
  },
  {
    "country": "Hungary",
    "retailer": "Douglas_HU",
    "parsing_config": "./retailer_config/Douglas/douglas_parsing.json",
    "gcloud_path": "crawl_data/Hungary/Douglas_HU/",
    "department": "Make Up",
    "category": "NAIL",
    "page": "Sets",
    "page_url": "https://www.douglas.hu/c/smink/korom/szettek/",
    "file_name": "Hungary_DOUGLAS_HU_MAKEUP_NAIL_Sets"
  },
  {
    "country": "Hungary",
    "retailer": "Douglas_HU",
    "parsing_config": "./retailer_config/Douglas/douglas_parsing.json",
    "gcloud_path": "crawl_data/Hungary/Douglas_HU/",
    "department": "Make Up",
    "category": "Accessories",
    "page": "Accessories",
    "page_url": "https://www.douglas.hu/c/smink/kiegeszitok/",
    "file_name": "Hungary_DOUGLAS_HU_MAKEUP_ACCESSORIES_ACCESSORIES"
  },
  {
    "country": "Hungary",
    "retailer": "Douglas_HU",
    "parsing_config": "./retailer_config/Douglas/douglas_parsing.json",
    "gcloud_path": "crawl_data/Hungary/Douglas_HU/",
    "department": "Make Up",
    "category": "Accessories",
    "page": "Make-up bags, toiletries",
    "page_url": "https://www.douglas.hu/c/smink/kiegeszitok/sminktaskak-neszesszerek/",
    "file_name": "Hungary_DOUGLAS_HU_MAKEUP_ACCESSORIES_Make|h|up|sp|bags,|sp|toiletries"
  },
  {
    "country": "Hungary",
    "retailer": "Douglas_HU",
    "parsing_config": "./retailer_config/Douglas/douglas_parsing.json",
    "gcloud_path": "crawl_data/Hungary/Douglas_HU/",
    "department": "Make Up",
    "category": "Accessories",
    "page": "Invite",
    "page_url": "https://www.douglas.hu/c/smink/kiegeszitok/ajak/",
    "file_name": "Hungary_DOUGLAS_HU_MAKEUP_ACCESSORIES_Invite"
  },
  {
    "country": "Hungary",
    "retailer": "Douglas_HU",
    "parsing_config": "./retailer_config/Douglas/douglas_parsing.json",
    "gcloud_path": "crawl_data/Hungary/Douglas_HU/",
    "department": "Make Up",
    "category": "Accessories",
    "page": "Eye",
    "page_url": "https://www.douglas.hu/c/smink/kiegeszitok/szem/",
    "file_name": "Hungary_DOUGLAS_HU_MAKEUP_ACCESSORIES_Eye"
  },
  {
    "country": "Hungary",
    "retailer": "Douglas_HU",
    "parsing_config": "./retailer_config/Douglas/douglas_parsing.json",
    "gcloud_path": "crawl_data/Hungary/Douglas_HU/",
    "department": "Make Up",
    "category": "Accessories",
    "page": "Arc",
    "page_url": "https://www.douglas.hu/c/smink/kiegeszitok/arc/",
    "file_name": "Hungary_DOUGLAS_HU_MAKEUP_ACCESSORIES_Arc"
  },
  {
    "country": "Hungary",
    "retailer": "Douglas_HU",
    "parsing_config": "./retailer_config/Douglas/douglas_parsing.json",
    "gcloud_path": "crawl_data/Hungary/Douglas_HU/",
    "department": "Make Up",
    "category": "Accessories",
    "page": "Nail",
    "page_url": "https://www.douglas.hu/c/smink/kiegeszitok/korom/",
    "file_name": "Hungary_DOUGLAS_HU_MAKEUP_ACCESSORIES_Nail"
  },
  {
    "country": "Hungary",
    "retailer": "Douglas_HU",
    "parsing_config": "./retailer_config/Douglas/douglas_parsing.json",
    "gcloud_path": "crawl_data/Hungary/Douglas_HU/",
    "department": "Make Up",
    "category": "Accessories",
    "page": "Sets",
    "page_url": "https://www.douglas.hu/c/smink/kiegeszitok/szettek/",
    "file_name": "Hungary_DOUGLAS_HU_MAKEUP_ACCESSORIES_Sets"
  },
  {
    "country": "Hungary",
    "retailer": "Douglas_HU",
    "parsing_config": "./retailer_config/Douglas/douglas_parsing.json",
    "gcloud_path": "crawl_data/Hungary/Douglas_HU/",
    "department": "Make Up",
    "category": "BRUSHES, SPONGES, APPLICATORS",
    "page": "BRUSHES, SPONGES, APPLICATORS",
    "page_url": "https://www.douglas.hu/c/smink/ecsetek-szivacsok-applikatorok/",
    "file_name": "Hungary_DOUGLAS_HU_MAKEUP_BRUSHES,|sp|SPONGES,|sp|APPLICATORS_BRUSHES,|sp|SPONGES,|sp|APPLICATORS"
  },
  {
    "country": "Hungary",
    "retailer": "Douglas_HU",
    "parsing_config": "./retailer_config/Douglas/douglas_parsing.json",
    "gcloud_path": "crawl_data/Hungary/Douglas_HU/",
    "department": "Make Up",
    "category": "BRUSHES, SPONGES, APPLICATORS",
    "page": "Sets, sets",
    "page_url": "https://www.douglas.hu/c/smink/ecsetek-szivacsok-applikatorok/keszletek-szettek/",
    "file_name": "Hungary_DOUGLAS_HU_MAKEUP_BRUSHES,|sp|SPONGES,|sp|APPLICATORS_Sets,|sp|sets"
  },
  {
    "country": "Hungary",
    "retailer": "Douglas_HU",
    "parsing_config": "./retailer_config/Douglas/douglas_parsing.json",
    "gcloud_path": "crawl_data/Hungary/Douglas_HU/",
    "department": "Make Up",
    "category": "BRUSHES, SPONGES, APPLICATORS",
    "page": "Blush, bronzer, highlighter brush",
    "page_url": "https://www.douglas.hu/c/smink/ecsetek-szivacsok-applikatorok/pirosito-bronzosito-highlighter-ecset/",
    "file_name": "Hungary_DOUGLAS_HU_MAKEUP_BRUSHES,|sp|SPONGES,|sp|APPLICATORS_Blush,|sp|bronzer,|sp|highlighter|sp|brush"
  },
  {
    "country": "Hungary",
    "retailer": "Douglas_HU",
    "parsing_config": "./retailer_config/Douglas/douglas_parsing.json",
    "gcloud_path": "crawl_data/Hungary/Douglas_HU/",
    "department": "Make Up",
    "category": "BRUSHES, SPONGES, APPLICATORS",
    "page": "Sponges",
    "page_url": "https://www.douglas.hu/c/smink/ecsetek-szivacsok-applikatorok/szivacsok/",
    "file_name": "Hungary_DOUGLAS_HU_MAKEUP_BRUSHES,|sp|SPONGES,|sp|APPLICATORS_Sponges"
  },
  {
    "country": "Hungary",
    "retailer": "Douglas_HU",
    "parsing_config": "./retailer_config/Douglas/douglas_parsing.json",
    "gcloud_path": "crawl_data/Hungary/Douglas_HU/",
    "department": "Make Up",
    "category": "BRUSHES, SPONGES, APPLICATORS",
    "page": "Eyeshadow brush",
    "page_url": "https://www.douglas.hu/c/smink/ecsetek-szivacsok-applikatorok/szemhejpuder-ecset/",
    "file_name": "Hungary_DOUGLAS_HU_MAKEUP_BRUSHES,|sp|SPONGES,|sp|APPLICATORS_Eyeshadow|sp|brush"
  },
  {
    "country": "Hungary",
    "retailer": "Douglas_HU",
    "parsing_config": "./retailer_config/Douglas/douglas_parsing.json",
    "gcloud_path": "crawl_data/Hungary/Douglas_HU/",
    "department": "Make Up",
    "category": "BRUSHES, SPONGES, APPLICATORS",
    "page": "Powder brush",
    "page_url": "https://www.douglas.hu/c/smink/ecsetek-szivacsok-applikatorok/puder-ecset/",
    "file_name": "Hungary_DOUGLAS_HU_MAKEUP_BRUSHES,|sp|SPONGES,|sp|APPLICATORS_Powder|sp|brush"
  },
  {
    "country": "Hungary",
    "retailer": "Douglas_HU",
    "parsing_config": "./retailer_config/Douglas/douglas_parsing.json",
    "gcloud_path": "crawl_data/Hungary/Douglas_HU/",
    "department": "Make Up",
    "category": "BRUSHES, SPONGES, APPLICATORS",
    "page": "Foundation brush",
    "page_url": "https://www.douglas.hu/c/smink/ecsetek-szivacsok-applikatorok/alapozo-ecset/",
    "file_name": "Hungary_DOUGLAS_HU_MAKEUP_BRUSHES,|sp|SPONGES,|sp|APPLICATORS_Foundation|sp|brush"
  },
  {
    "country": "Hungary",
    "retailer": "Douglas_HU",
    "parsing_config": "./retailer_config/Douglas/douglas_parsing.json",
    "gcloud_path": "crawl_data/Hungary/Douglas_HU/",
    "department": "Make Up",
    "category": "BRUSHES, SPONGES, APPLICATORS",
    "page": "Lipstick brush",
    "page_url": "https://www.douglas.hu/c/smink/ecsetek-szivacsok-applikatorok/ruzsecset/",
    "file_name": "Hungary_DOUGLAS_HU_MAKEUP_BRUSHES,|sp|SPONGES,|sp|APPLICATORS_Lipstick|sp|brush"
  },
  {
    "country": "Hungary",
    "retailer": "Douglas_HU",
    "parsing_config": "./retailer_config/Douglas/douglas_parsing.json",
    "gcloud_path": "crawl_data/Hungary/Douglas_HU/",
    "department": "Make Up",
    "category": "BRUSHES, SPONGES, APPLICATORS",
    "page": "Eyeliner brush",
    "page_url": "https://www.douglas.hu/c/smink/ecsetek-szivacsok-applikatorok/szemceruza-ecset/",
    "file_name": "Hungary_DOUGLAS_HU_MAKEUP_BRUSHES,|sp|SPONGES,|sp|APPLICATORS_Eyeliner|sp|brush"
  },
  {
    "country": "Hungary",
    "retailer": "Douglas_HU",
    "parsing_config": "./retailer_config/Douglas/douglas_parsing.json",
    "gcloud_path": "crawl_data/Hungary/Douglas_HU/",
    "department": "Make Up",
    "category": "BRUSHES, SPONGES, APPLICATORS",
    "page": "Brush cleaning",
    "page_url": "https://www.douglas.hu/c/smink/ecsetek-szivacsok-applikatorok/ecsettisztitas/",
    "file_name": "Hungary_DOUGLAS_HU_MAKEUP_BRUSHES,|sp|SPONGES,|sp|APPLICATORS_Brush|sp|cleaning"
  },
  {
    "country": "Hungary",
    "retailer": "Douglas_HU",
    "parsing_config": "./retailer_config/Douglas/douglas_parsing.json",
    "gcloud_path": "crawl_data/Hungary/Douglas_HU/",
    "department": "Make Up",
    "category": "BRUSHES, SPONGES, APPLICATORS",
    "page": "Concealer brush",
    "page_url": "https://www.douglas.hu/c/smink/ecsetek-szivacsok-applikatorok/korrektor-ecset/",
    "file_name": "Hungary_DOUGLAS_HU_MAKEUP_BRUSHES,|sp|SPONGES,|sp|APPLICATORS_Concealer|sp|brush"
  },
  {
    "country": "Hungary",
    "retailer": "Douglas_HU",
    "parsing_config": "./retailer_config/Douglas/douglas_parsing.json",
    "gcloud_path": "crawl_data/Hungary/Douglas_HU/",
    "department": "Make Up",
    "category": "BRUSHES, SPONGES, APPLICATORS",
    "page": "Contour brush",
    "page_url": "https://www.douglas.hu/c/smink/ecsetek-szivacsok-applikatorok/kontur-ecset/",
    "file_name": "Hungary_DOUGLAS_HU_MAKEUP_BRUSHES,|sp|SPONGES,|sp|APPLICATORS_Contour|sp|brush"
  },
  {
    "country": "Hungary",
    "retailer": "Douglas_HU",
    "parsing_config": "./retailer_config/Douglas/douglas_parsing.json",
    "gcloud_path": "crawl_data/Hungary/Douglas_HU/",
    "department": "Make Up",
    "category": "BRUSHES, SPONGES, APPLICATORS",
    "page": "All categories",
    "page_url": "https://www.douglas.hu/c/smink/ecsetek-szivacsok-applikatorok/",
    "file_name": "Hungary_DOUGLAS_HU_MAKEUP_BRUSHES,|sp|SPONGES,|sp|APPLICATORS_All|sp|categories"
  },
  {
    "country": "Hungary",
    "retailer": "Douglas_HU",
    "parsing_config": "./retailer_config/Douglas/douglas_parsing.json",
    "gcloud_path": "crawl_data/Hungary/Douglas_HU/",
    "department": "Make Up",
    "category": "TEST MINK",
    "page": "TEST MINK",
    "page_url": "https://www.douglas.hu/c/smink/testsmink/",
    "file_name": "Hungary_DOUGLAS_HU_MAKEUP_TEST|sp|MINK_TEST|sp|MINK"
  },
  {
    "country": "Hungary",
    "retailer": "Douglas_HU",
    "parsing_config": "./retailer_config/Douglas/douglas_parsing.json",
    "gcloud_path": "crawl_data/Hungary/Douglas_HU/",
    "department": "HAJ",
    "category": "HAJ",
    "page": "HAJ",
    "page_url": "https://www.douglas.hu/c/haj/",
    "file_name": "Hungary_DOUGLAS_HU_HAJ_HAJ_HAJ"
  },
  {
    "country": "Hungary",
    "retailer": "Douglas_HU",
    "parsing_config": "./retailer_config/Douglas/douglas_parsing.json",
    "gcloud_path": "crawl_data/Hungary/Douglas_HU/",
    "department": "HAJ",
    "category": "Haircare",
    "page": "Haircare",
    "page_url": "https://www.douglas.hu/c/haj/hajapolas/",
    "file_name": "Hungary_DOUGLAS_HU_HAJ_HAIR|sp|CARE_HAIR|sp|CARE"
  },
  {
    "country": "Hungary",
    "retailer": "Douglas_HU",
    "parsing_config": "./retailer_config/Douglas/douglas_parsing.json",
    "gcloud_path": "crawl_data/Hungary/Douglas_HU/",
    "department": "HAJ",
    "category": "Haircare",
    "page": "Shampoo",
    "page_url": "https://www.douglas.hu/c/haj/hajapolas/sampon/",
    "file_name": "Hungary_DOUGLAS_HU_HAJ_HAIR|sp|CARE_Shampoo"
  },
  {
    "country": "Hungary",
    "retailer": "Douglas_HU",
    "parsing_config": "./retailer_config/Douglas/douglas_parsing.json",
    "gcloud_path": "crawl_data/Hungary/Douglas_HU/",
    "department": "HAJ",
    "category": "Haircare",
    "page": "Dry shampoo",
    "page_url": "https://www.douglas.hu/c/haj/hajapolas/szarazsampon/",
    "file_name": "Hungary_DOUGLAS_HU_HAJ_HAIR|sp|CARE_Dry|sp|shampoo"
  },
  {
    "country": "Hungary",
    "retailer": "Douglas_HU",
    "parsing_config": "./retailer_config/Douglas/douglas_parsing.json",
    "gcloud_path": "crawl_data/Hungary/Douglas_HU/",
    "department": "HAJ",
    "category": "Haircare",
    "page": "Hair conditioner & conditioner",
    "page_url": "https://www.douglas.hu/c/haj/hajapolas/hajbalzsam-kondicionalo/",
    "file_name": "Hungary_DOUGLAS_HU_HAJ_HAIR|sp|CARE_Hair|sp|conditioner|sp||as||sp|conditioner"
  },
  {
    "country": "Hungary",
    "retailer": "Douglas_HU",
    "parsing_config": "./retailer_config/Douglas/douglas_parsing.json",
    "gcloud_path": "crawl_data/Hungary/Douglas_HU/",
    "department": "HAJ",
    "category": "Haircare",
    "page": "Does not require rinsing",
    "page_url": "https://www.douglas.hu/c/haj/hajapolas/oblitest-nem-igenylo/",
    "file_name": "Hungary_DOUGLAS_HU_HAJ_HAIR|sp|CARE_Does|sp|not|sp|require|sp|rinsing"
  },
  {
    "country": "Hungary",
    "retailer": "Douglas_HU",
    "parsing_config": "./retailer_config/Douglas/douglas_parsing.json",
    "gcloud_path": "crawl_data/Hungary/Douglas_HU/",
    "department": "HAJ",
    "category": "Haircare",
    "page": "Hair treatment & mask",
    "page_url": "https://www.douglas.hu/c/haj/hajapolas/hajkezeles-maszk/",
    "file_name": "Hungary_DOUGLAS_HU_HAJ_HAIR|sp|CARE_Hair|sp|treatment|sp||as||sp|mask"
  },
  {
    "country": "Hungary",
    "retailer": "Douglas_HU",
    "parsing_config": "./retailer_config/Douglas/douglas_parsing.json",
    "gcloud_path": "crawl_data/Hungary/Douglas_HU/",
    "department": "HAJ",
    "category": "Haircare",
    "page": "Scalp care",
    "page_url": "https://www.douglas.hu/c/haj/hajapolas/fejbor-apolas/",
    "file_name": "Hungary_DOUGLAS_HU_HAJ_HAIR|sp|CARE_Scalp|sp|care"
  },
  {
    "country": "Hungary",
    "retailer": "Douglas_HU",
    "parsing_config": "./retailer_config/Douglas/douglas_parsing.json",
    "gcloud_path": "crawl_data/Hungary/Douglas_HU/",
    "department": "HAJ",
    "category": "Shampoo",
    "page": "Shampoo",
    "page_url": "https://www.douglas.hu/c/haj/sampon/",
    "file_name": "Hungary_DOUGLAS_HU_HAJ_SHAMPOO_SHAMPOO"
  },
  {
    "country": "Hungary",
    "retailer": "Douglas_HU",
    "parsing_config": "./retailer_config/Douglas/douglas_parsing.json",
    "gcloud_path": "crawl_data/Hungary/Douglas_HU/",
    "department": "HAJ",
    "category": "Shampoo",
    "page": "For normal hair",
    "page_url": "https://www.douglas.hu/c/haj/sampon/normal-hajra/",
    "file_name": "Hungary_DOUGLAS_HU_HAJ_SHAMPOO_For|sp|normal|sp|hair"
  },
  {
    "country": "Hungary",
    "retailer": "Douglas_HU",
    "parsing_config": "./retailer_config/Douglas/douglas_parsing.json",
    "gcloud_path": "crawl_data/Hungary/Douglas_HU/",
    "department": "HAJ",
    "category": "Shampoo",
    "page": "For used, dry hair",
    "page_url": "https://www.douglas.hu/c/haj/sampon/igenybevett-szaraz-hajra/",
    "file_name": "Hungary_DOUGLAS_HU_HAJ_SHAMPOO_For|sp|used,|sp|dry|sp|hair"
  },
  {
    "country": "Hungary",
    "retailer": "Douglas_HU",
    "parsing_config": "./retailer_config/Douglas/douglas_parsing.json",
    "gcloud_path": "crawl_data/Hungary/Douglas_HU/",
    "department": "HAJ",
    "category": "Shampoo",
    "page": "For colored / dyed hair",
    "page_url": "https://www.douglas.hu/c/haj/sampon/szinezett-festett-hajra/",
    "file_name": "Hungary_DOUGLAS_HU_HAJ_SHAMPOO_For|sp|colored|sp||fs||sp|dyed|sp|hair"
  },
  {
    "country": "Hungary",
    "retailer": "Douglas_HU",
    "parsing_config": "./retailer_config/Douglas/douglas_parsing.json",
    "gcloud_path": "crawl_data/Hungary/Douglas_HU/",
    "department": "HAJ",
    "category": "Shampoo",
    "page": "Dry shampoos",
    "page_url": "https://www.douglas.hu/c/haj/sampon/szarazsamponok/",
    "file_name": "Hungary_DOUGLAS_HU_HAJ_SHAMPOO_Dry|sp|shampoos"
  },
  {
    "country": "Hungary",
    "retailer": "Douglas_HU",
    "parsing_config": "./retailer_config/Douglas/douglas_parsing.json",
    "gcloud_path": "crawl_data/Hungary/Douglas_HU/",
    "department": "HAJ",
    "category": "By Hair Type",
    "page": "By Hair Type",
    "page_url": "https://www.douglas.hu/c/haj/hajtipus-szerint/",
    "file_name": "Hungary_DOUGLAS_HU_HAJ_BY|sp|HAIR|sp|TYPE_BY|sp|HAIR|sp|TYPE"
  },
  {
    "country": "Hungary",
    "retailer": "Douglas_HU",
    "parsing_config": "./retailer_config/Douglas/douglas_parsing.json",
    "gcloud_path": "crawl_data/Hungary/Douglas_HU/",
    "department": "HAJ",
    "category": "By Hair Type",
    "page": "For normal hair",
    "page_url": "https://www.douglas.hu/c/haj/hajtipus-szerint/normal-hajra/",
    "file_name": "Hungary_DOUGLAS_HU_HAJ_BY|sp|HAIR|sp|TYPE_For|sp|normal|sp|hair"
  },
  {
    "country": "Hungary",
    "retailer": "Douglas_HU",
    "parsing_config": "./retailer_config/Douglas/douglas_parsing.json",
    "gcloud_path": "crawl_data/Hungary/Douglas_HU/",
    "department": "HAJ",
    "category": "By Hair Type",
    "page": "For dry, split ends",
    "page_url": "https://www.douglas.hu/c/haj/hajtipus-szerint/szaraz-toredezett-hajra/",
    "file_name": "Hungary_DOUGLAS_HU_HAJ_BY|sp|HAIR|sp|TYPE_For|sp|dry,|sp|split|sp|ends"
  },
  {
    "country": "Hungary",
    "retailer": "Douglas_HU",
    "parsing_config": "./retailer_config/Douglas/douglas_parsing.json",
    "gcloud_path": "crawl_data/Hungary/Douglas_HU/",
    "department": "HAJ",
    "category": "By Hair Type",
    "page": "For colored / dyed hair",
    "page_url": "https://www.douglas.hu/c/haj/hajtipus-szerint/szinezett-festett-hajra/",
    "file_name": "Hungary_DOUGLAS_HU_HAJ_BY|sp|HAIR|sp|TYPE_For|sp|colored|sp||fs||sp|dyed|sp|hair"
  },
  {
    "country": "Hungary",
    "retailer": "Douglas_HU",
    "parsing_config": "./retailer_config/Douglas/douglas_parsing.json",
    "gcloud_path": "crawl_data/Hungary/Douglas_HU/",
    "department": "HAJ",
    "category": "By Hair Type",
    "page": "For greasy hair",
    "page_url": "https://www.douglas.hu/c/haj/hajtipus-szerint/zsiros-hajra/",
    "file_name": "Hungary_DOUGLAS_HU_HAJ_BY|sp|HAIR|sp|TYPE_For|sp|greasy|sp|hair"
  },
  {
    "country": "Hungary",
    "retailer": "Douglas_HU",
    "parsing_config": "./retailer_config/Douglas/douglas_parsing.json",
    "gcloud_path": "crawl_data/Hungary/Douglas_HU/",
    "department": "HAJ",
    "category": "By Hair Type",
    "page": "For thin hair",
    "page_url": "https://www.douglas.hu/c/haj/hajtipus-szerint/vekony-hajra/",
    "file_name": "Hungary_DOUGLAS_HU_HAJ_BY|sp|HAIR|sp|TYPE_For|sp|thin|sp|hair"
  },
  {
    "country": "Hungary",
    "retailer": "Douglas_HU",
    "parsing_config": "./retailer_config/Douglas/douglas_parsing.json",
    "gcloud_path": "crawl_data/Hungary/Douglas_HU/",
    "department": "HAJ",
    "category": "By Hair Type",
    "page": "For curly hair",
    "page_url": "https://www.douglas.hu/c/haj/hajtipus-szerint/gondor-hajra/",
    "file_name": "Hungary_DOUGLAS_HU_HAJ_BY|sp|HAIR|sp|TYPE_For|sp|curly|sp|hair"
  },
  {
    "country": "Hungary",
    "retailer": "Douglas_HU",
    "parsing_config": "./retailer_config/Douglas/douglas_parsing.json",
    "gcloud_path": "crawl_data/Hungary/Douglas_HU/",
    "department": "HAJ",
    "category": "By Hair Type",
    "page": "Against hair loss",
    "page_url": "https://www.douglas.hu/c/haj/hajtipus-szerint/hajhullas-ellen/",
    "file_name": "Hungary_DOUGLAS_HU_HAJ_BY|sp|HAIR|sp|TYPE_Against|sp|hair|sp|loss"
  },
  {
    "country": "Hungary",
    "retailer": "Douglas_HU",
    "parsing_config": "./retailer_config/Douglas/douglas_parsing.json",
    "gcloud_path": "crawl_data/Hungary/Douglas_HU/",
    "department": "HAJ",
    "category": "By Hair Type",
    "page": "For hair that is difficult to handle",
    "page_url": "https://www.douglas.hu/c/haj/hajtipus-szerint/nehezen-kezelhezo-hajra/",
    "file_name": "Hungary_DOUGLAS_HU_HAJ_BY|sp|HAIR|sp|TYPE_For|sp|hair|sp|that|sp|is|sp|difficult|sp|to|sp|handle"
  },
  {
    "country": "Hungary",
    "retailer": "Douglas_HU",
    "parsing_config": "./retailer_config/Douglas/douglas_parsing.json",
    "gcloud_path": "crawl_data/Hungary/Douglas_HU/",
    "department": "HAJ",
    "category": "By Hair Type",
    "page": "Against dandruff",
    "page_url": "https://www.douglas.hu/c/haj/hajtipus-szerint/korpasodas-ellen/",
    "file_name": "Hungary_DOUGLAS_HU_HAJ_BY|sp|HAIR|sp|TYPE_Against|sp|dandruff"
  },
  {
    "country": "Hungary",
    "retailer": "Douglas_HU",
    "parsing_config": "./retailer_config/Douglas/douglas_parsing.json",
    "gcloud_path": "crawl_data/Hungary/Douglas_HU/",
    "department": "HAJ",
    "category": "By Hair Type",
    "page": "For sensitive scalp",
    "page_url": "https://www.douglas.hu/c/haj/hajtipus-szerint/erzekeny-fejborre/",
    "file_name": "Hungary_DOUGLAS_HU_HAJ_BY|sp|HAIR|sp|TYPE_For|sp|sensitive|sp|scalp"
  },
  {
    "country": "Hungary",
    "retailer": "Douglas_HU",
    "parsing_config": "./retailer_config/Douglas/douglas_parsing.json",
    "gcloud_path": "crawl_data/Hungary/Douglas_HU/",
    "department": "HAJ",
    "category": "Hair Styling",
    "page": "Hair Styling",
    "page_url": "https://www.douglas.hu/c/haj/hajformazas/",
    "file_name": "Hungary_DOUGLAS_HU_HAJ_HAIR|sp|STYLING_HAIR|sp|STYLING"
  },
  {
    "country": "Hungary",
    "retailer": "Douglas_HU",
    "parsing_config": "./retailer_config/Douglas/douglas_parsing.json",
    "gcloud_path": "crawl_data/Hungary/Douglas_HU/",
    "department": "HAJ",
    "category": "Hair Styling",
    "page": "Spray & Permet",
    "page_url": "https://www.douglas.hu/c/haj/hajformazas/spray-permet/",
    "file_name": "Hungary_DOUGLAS_HU_HAJ_HAIR|sp|STYLING_Spray|sp||as||sp|Permet"
  },
  {
    "country": "Hungary",
    "retailer": "Douglas_HU",
    "parsing_config": "./retailer_config/Douglas/douglas_parsing.json",
    "gcloud_path": "crawl_data/Hungary/Douglas_HU/",
    "department": "HAJ",
    "category": "Hair Styling",
    "page": "Jelly & foam & cream",
    "page_url": "https://www.douglas.hu/c/haj/hajformazas/zsele-hab-krem/",
    "file_name": "Hungary_DOUGLAS_HU_HAJ_HAIR|sp|STYLING_Jelly|sp||as||sp|foam|sp||as||sp|cream"
  },
  {
    "country": "Hungary",
    "retailer": "Douglas_HU",
    "parsing_config": "./retailer_config/Douglas/douglas_parsing.json",
    "gcloud_path": "crawl_data/Hungary/Douglas_HU/",
    "department": "HAJ",
    "category": "Hair Styling",
    "page": "Combs",
    "page_url": "https://www.douglas.hu/c/haj/hajformazas/fesuk/",
    "file_name": "Hungary_DOUGLAS_HU_HAJ_HAIR|sp|STYLING_Combs"
  },
  {
    "country": "Hungary",
    "retailer": "Douglas_HU",
    "parsing_config": "./retailer_config/Douglas/douglas_parsing.json",
    "gcloud_path": "crawl_data/Hungary/Douglas_HU/",
    "department": "HAJ",
    "category": "Hair Styling",
    "page": "Accessories",
    "page_url": "https://www.douglas.hu/c/haj/hajformazas/kiegeszitok/",
    "file_name": "Hungary_DOUGLAS_HU_HAJ_HAIR|sp|STYLING_Accessories"
  },
  {
    "country": "Hungary",
    "retailer": "Douglas_HU",
    "parsing_config": "./retailer_config/Douglas/douglas_parsing.json",
    "gcloud_path": "crawl_data/Hungary/Douglas_HU/",
    "department": "HAJ",
    "category": "Hair Styling",
    "page": "Curling iron",
    "page_url": "https://www.douglas.hu/c/haj/hajformazas/hajsutovas/",
    "file_name": "Hungary_DOUGLAS_HU_HAJ_HAIR|sp|STYLING_Curling|sp|iron"
  },
  {
    "country": "Hungary",
    "retailer": "Douglas_HU",
    "parsing_config": "./retailer_config/Douglas/douglas_parsing.json",
    "gcloud_path": "crawl_data/Hungary/Douglas_HU/",
    "department": "HAJ",
    "category": "Hair Styling",
    "page": "Hair straightener",
    "page_url": "https://www.douglas.hu/c/haj/hajformazas/hajvasalo/",
    "file_name": "Hungary_DOUGLAS_HU_HAJ_HAIR|sp|STYLING_Hair|sp|straightener"
  },
  {
    "country": "Hungary",
    "retailer": "Douglas_HU",
    "parsing_config": "./retailer_config/Douglas/douglas_parsing.json",
    "gcloud_path": "crawl_data/Hungary/Douglas_HU/",
    "department": "HAJ",
    "category": "Hair Styling",
    "page": "Hair curler",
    "page_url": "https://www.douglas.hu/c/haj/hajformazas/hajgondorito/",
    "file_name": "Hungary_DOUGLAS_HU_HAJ_HAIR|sp|STYLING_Hair|sp|curler"
  },
  {
    "country": "Hungary",
    "retailer": "Douglas_HU",
    "parsing_config": "./retailer_config/Douglas/douglas_parsing.json",
    "gcloud_path": "crawl_data/Hungary/Douglas_HU/",
    "department": "HAJ",
    "category": "Hair Styling",
    "page": "Hair clipper / beard trimmer",
    "page_url": "https://www.douglas.hu/c/haj/hajformazas/hajvagoszakallvago/",
    "file_name": "Hungary_DOUGLAS_HU_HAJ_HAIR|sp|STYLING_Hair|sp|clipper|sp||fs||sp|beard|sp|trimmer"
  },
  {
    "country": "Hungary",
    "retailer": "Douglas_HU",
    "parsing_config": "./retailer_config/Douglas/douglas_parsing.json",
    "gcloud_path": "crawl_data/Hungary/Douglas_HU/",
    "department": "HAJ",
    "category": "Hair Styling",
    "page": "Hair dryer",
    "page_url": "https://www.douglas.hu/c/haj/hajformazas/hajszarito/",
    "file_name": "Hungary_DOUGLAS_HU_HAJ_HAIR|sp|STYLING_Hair|sp|dryer"
  },
  {
    "country": "Hungary",
    "retailer": "Douglas_HU",
    "parsing_config": "./retailer_config/Douglas/douglas_parsing.json",
    "gcloud_path": "crawl_data/Hungary/Douglas_HU/",
    "department": "HAJ",
    "category": "HAIR COLORING, COLORING",
    "page": "HAIR COLORING, COLORING",
    "page_url": "https://www.douglas.hu/c/haj/hajfestes-szinezes/",
    "file_name": "Hungary_DOUGLAS_HU_HAJ_HAIR|sp|COLORING,|sp|COLORING_HAIR|sp|COLORING,|sp|COLORING"
  },
  {
    "country": "Hungary",
    "retailer": "Douglas_HU",
    "parsing_config": "./retailer_config/Douglas/douglas_parsing.json",
    "gcloud_path": "crawl_data/Hungary/Douglas_HU/",
    "department": "Home & Lifestyle",
    "category": "Home & Lifestyle",
    "page": "Home & Lifestyle",
    "page_url": "https://www.douglas.hu/c/home-lifestyle/",
    "file_name": "Hungary_DOUGLAS_HU_HOME|sp||as||sp|LIFESTYLE_HOME|sp||as||sp|LIFESTYLE_HOME|sp||as||sp|LIFESTYLE"
  },
  {
    "country": "Hungary",
    "retailer": "Douglas_HU",
    "parsing_config": "./retailer_config/Douglas/douglas_parsing.json",
    "gcloud_path": "crawl_data/Hungary/Douglas_HU/",
    "department": "Home & Lifestyle",
    "category": "Jewellery",
    "page": "Jewellery",
    "page_url": "https://www.douglas.hu/c/home-lifestyle/ekszerek/",
    "file_name": "Hungary_DOUGLAS_HU_HOME|sp||as||sp|LIFESTYLE_JEWELRY_JEWELRY"
  },
  {
    "country": "Hungary",
    "retailer": "Douglas_HU",
    "parsing_config": "./retailer_config/Douglas/douglas_parsing.json",
    "gcloud_path": "crawl_data/Hungary/Douglas_HU/",
    "department": "Home & Lifestyle",
    "category": "Jewellery",
    "page": "Bracelet",
    "page_url": "https://www.douglas.hu/c/home-lifestyle/ekszerek/karkoto/",
    "file_name": "Hungary_DOUGLAS_HU_HOME|sp||as||sp|LIFESTYLE_JEWELRY_Bracelet"
  },
  {
    "country": "Hungary",
    "retailer": "Douglas_HU",
    "parsing_config": "./retailer_config/Douglas/douglas_parsing.json",
    "gcloud_path": "crawl_data/Hungary/Douglas_HU/",
    "department": "Home & Lifestyle",
    "category": "Jewellery",
    "page": "Earrings",
    "page_url": "https://www.douglas.hu/c/home-lifestyle/ekszerek/fulbevalo/",
    "file_name": "Hungary_DOUGLAS_HU_HOME|sp||as||sp|LIFESTYLE_JEWELRY_Earrings"
  },
  {
    "country": "Hungary",
    "retailer": "Douglas_HU",
    "parsing_config": "./retailer_config/Douglas/douglas_parsing.json",
    "gcloud_path": "crawl_data/Hungary/Douglas_HU/",
    "department": "Home & Lifestyle",
    "category": "Fragrance",
    "page": "Fragrance",
    "page_url": "https://www.douglas.hu/c/home-lifestyle/illatositok/",
    "file_name": "Hungary_DOUGLAS_HU_HOME|sp||as||sp|LIFESTYLE_FRAGRANCES_FRAGRANCES"
  },
  {
    "country": "Hungary",
    "retailer": "Douglas_HU",
    "parsing_config": "./retailer_config/Douglas/douglas_parsing.json",
    "gcloud_path": "crawl_data/Hungary/Douglas_HU/",
    "department": "Home & Lifestyle",
    "category": "Fragrance",
    "page": "Illatgyertya",
    "page_url": "https://www.douglas.hu/c/home-lifestyle/illatositok/illatgyertya/",
    "file_name": "Hungary_DOUGLAS_HU_HOME|sp||as||sp|LIFESTYLE_FRAGRANCES_Illatgyertya"
  },
  {
    "country": "Hungary",
    "retailer": "Douglas_HU",
    "parsing_config": "./retailer_config/Douglas/douglas_parsing.json",
    "gcloud_path": "crawl_data/Hungary/Douglas_HU/",
    "department": "Home & Lifestyle",
    "category": "Fragrance",
    "page": "Aroma diffuser",
    "page_url": "https://www.douglas.hu/c/home-lifestyle/illatositok/aroma-diffuzor/",
    "file_name": "Hungary_DOUGLAS_HU_HOME|sp||as||sp|LIFESTYLE_FRAGRANCES_Aroma|sp|diffuser"
  },
  {
    "country": "Hungary",
    "retailer": "Douglas_HU",
    "parsing_config": "./retailer_config/Douglas/douglas_parsing.json",
    "gcloud_path": "crawl_data/Hungary/Douglas_HU/",
    "department": "Home & Lifestyle",
    "category": "Fragrance",
    "page": "Home perfume",
    "page_url": "https://www.douglas.hu/c/home-lifestyle/illatositok/lakasparfum/",
    "file_name": "Hungary_DOUGLAS_HU_HOME|sp||as||sp|LIFESTYLE_FRAGRANCES_Home|sp|perfume"
  },
  {
    "country": "Hungary",
    "retailer": "Douglas_HU",
    "parsing_config": "./retailer_config/Douglas/douglas_parsing.json",
    "gcloud_path": "crawl_data/Hungary/Douglas_HU/",
    "department": "Home & Lifestyle",
    "category": "Fragrance",
    "page": "Car perfume",
    "page_url": "https://www.douglas.hu/c/home-lifestyle/illatositok/autoillatosito/",
    "file_name": "Hungary_DOUGLAS_HU_HOME|sp||as||sp|LIFESTYLE_FRAGRANCES_Car|sp|perfume"
  },
  {
    "country": "Hungary",
    "retailer": "Douglas_HU",
    "parsing_config": "./retailer_config/Douglas/douglas_parsing.json",
    "gcloud_path": "crawl_data/Hungary/Douglas_HU/",
    "department": "Accessories",
    "category": "Accessories",
    "page": "Accessories",
    "page_url": "https://www.douglas.hu/c/kiegeszitok/",
    "file_name": "Hungary_DOUGLAS_HU_ACCESSORIES_ACCESSORIES_ACCESSORIES"
  },
  {
    "country": "Hungary",
    "retailer": "Douglas_HU",
    "parsing_config": "./retailer_config/Douglas/douglas_parsing.json",
    "gcloud_path": "crawl_data/Hungary/Douglas_HU/",
    "department": "Accessories",
    "category": "Accessories",
    "page": "Accessories",
    "page_url": "https://www.douglas.hu/c/kiegeszitok/kiegeszitok/",
    "file_name": "Hungary_DOUGLAS_HU_ACCESSORIES_ACCESSORIES_ACCESSORIES"
  },
  {
    "country": "Hungary",
    "retailer": "Douglas_HU",
    "parsing_config": "./retailer_config/Douglas/douglas_parsing.json",
    "gcloud_path": "crawl_data/Hungary/Douglas_HU/",
    "department": "Exclusive",
    "category": "Exclusive",
    "page": "Exclusive",
    "page_url": "https://www.douglas.hu/c/exkluziv/",
    "file_name": "Hungary_DOUGLAS_HU_EXCLUSIVE_EXCLUSIVE_EXCLUSIVE"
  },
  {
    "country": "Hungary",
    "retailer": "Douglas_HU",
    "parsing_config": "./retailer_config/Douglas/douglas_parsing.json",
    "gcloud_path": "crawl_data/Hungary/Douglas_HU/",
    "department": "Exclusive",
    "category": "DOUGLAS EXCLUSIVE",
    "page": "DOUGLAS EXCLUSIVE",
    "page_url": "https://www.douglas.hu/c/exkluziv/douglas-exkluziv/",
    "file_name": "Hungary_DOUGLAS_HU_EXCLUSIVE_DOUGLAS|sp|EXCLUSIVE_DOUGLAS|sp|EXCLUSIVE"
  },
  {
    "country": "Hungary",
    "retailer": "Douglas_HU",
    "parsing_config": "./retailer_config/Douglas/douglas_parsing.json",
    "gcloud_path": "crawl_data/Hungary/Douglas_HU/",
    "department": "Exclusive",
    "category": "ONLINE EXCLUSIVE",
    "page": "ONLINE EXCLUSIVE",
    "page_url": "https://www.douglas.hu/c/exkluziv/online-exkluziv/",
    "file_name": "Hungary_DOUGLAS_HU_EXCLUSIVE_ONLINE|sp|EXCLUSIVE_ONLINE|sp|EXCLUSIVE"
  },
  {
    "country": "Hungary",
    "retailer": "Douglas_HU",
    "parsing_config": "./retailer_config/Douglas/douglas_parsing.json",
    "gcloud_path": "crawl_data/Hungary/Douglas_HU/",
    "department": "New Products",
    "category": "New Products",
    "page": "New Products",
    "page_url": "https://www.douglas.hu/c/uj-termekek/",
    "file_name": "Hungary_DOUGLAS_HU_NEW|sp|PRODUCTS_NEW|sp|PRODUCTS_NEW|sp|PRODUCTS"
  },
  {
    "country": "Hungary",
    "retailer": "Douglas_HU",
    "parsing_config": "./retailer_config/Douglas/douglas_parsing.json",
    "gcloud_path": "crawl_data/Hungary/Douglas_HU/",
    "department": "New Brands",
    "category": "New Brands",
    "page": "New Brands",
    "page_url": "https://www.douglas.hu/c/uj-markak/",
    "file_name": "Hungary_DOUGLAS_HU_NEW|sp|BRANDS_NEW|sp|BRANDS_NEW|sp|BRANDS"
  },
  {
    "country": "Hungary",
    "retailer": "Douglas_HU",
    "parsing_config": "./retailer_config/Douglas/douglas_parsing.json",
    "gcloud_path": "crawl_data/Hungary/Douglas_HU/",
    "department": "New Brands",
    "category": "ARGANICARE",
    "page": "ARGANICARE",
    "page_url": "https://www.douglas.hu/c/uj-markak/arganicare/",
    "file_name": "Hungary_DOUGLAS_HU_NEW|sp|BRANDS_ARGANICARE_ARGANICARE"
  },
  {
    "country": "Hungary",
    "retailer": "Douglas_HU",
    "parsing_config": "./retailer_config/Douglas/douglas_parsing.json",
    "gcloud_path": "crawl_data/Hungary/Douglas_HU/",
    "department": "New Brands",
    "category": "ATKINSONS",
    "page": "ATKINSONS",
    "page_url": "https://www.douglas.hu/c/uj-markak/atkinsons/",
    "file_name": "Hungary_DOUGLAS_HU_NEW|sp|BRANDS_ATKINSONS_ATKINSONS"
  },
  {
    "country": "Hungary",
    "retailer": "Douglas_HU",
    "parsing_config": "./retailer_config/Douglas/douglas_parsing.json",
    "gcloud_path": "crawl_data/Hungary/Douglas_HU/",
    "department": "New Brands",
    "category": "BABYLISS",
    "page": "BABYLISS",
    "page_url": "https://www.douglas.hu/c/uj-markak/babyliss/",
    "file_name": "Hungary_DOUGLAS_HU_NEW|sp|BRANDS_BABYLISS_BABYLISS"
  },
  {
    "country": "Hungary",
    "retailer": "Douglas_HU",
    "parsing_config": "./retailer_config/Douglas/douglas_parsing.json",
    "gcloud_path": "crawl_data/Hungary/Douglas_HU/",
    "department": "New Brands",
    "category": "CHOPARD",
    "page": "CHOPARD",
    "page_url": "https://www.douglas.hu/c/uj-markak/chopard/",
    "file_name": "Hungary_DOUGLAS_HU_NEW|sp|BRANDS_CHOPARD_CHOPARD"
  },
  {
    "country": "Hungary",
    "retailer": "Douglas_HU",
    "parsing_config": "./retailer_config/Douglas/douglas_parsing.json",
    "gcloud_path": "crawl_data/Hungary/Douglas_HU/",
    "department": "New Brands",
    "category": "DSQUARED2",
    "page": "DSQUARED2",
    "page_url": "https://www.douglas.hu/c/uj-markak/dsquared2/",
    "file_name": "Hungary_DOUGLAS_HU_NEW|sp|BRANDS_DSQUARED2_DSQUARED2"
  },
  {
    "country": "Hungary",
    "retailer": "Douglas_HU",
    "parsing_config": "./retailer_config/Douglas/douglas_parsing.json",
    "gcloud_path": "crawl_data/Hungary/Douglas_HU/",
    "department": "New Brands",
    "category": "GOSH COPENHAGEN",
    "page": "GOSH COPENHAGEN",
    "page_url": "https://www.douglas.hu/c/uj-markak/gosh-copenhagen/",
    "file_name": "Hungary_DOUGLAS_HU_NEW|sp|BRANDS_GOSH|sp|COPENHAGEN_GOSH|sp|COPENHAGEN"
  },
  {
    "country": "Hungary",
    "retailer": "Douglas_HU",
    "parsing_config": "./retailer_config/Douglas/douglas_parsing.json",
    "gcloud_path": "crawl_data/Hungary/Douglas_HU/",
    "department": "New Brands",
    "category": "JORGOBE",
    "page": "JORGOBE",
    "page_url": "https://www.douglas.hu/c/uj-markak/jorgobe/",
    "file_name": "Hungary_DOUGLAS_HU_NEW|sp|BRANDS_JORGOBE_JORGOBE"
  },
  {
    "country": "Hungary",
    "retailer": "Douglas_HU",
    "parsing_config": "./retailer_config/Douglas/douglas_parsing.json",
    "gcloud_path": "crawl_data/Hungary/Douglas_HU/",
    "department": "New Brands",
    "category": "JUICE BEAUTY",
    "page": "JUICE BEAUTY",
    "page_url": "https://www.douglas.hu/c/uj-markak/juice-beauty/",
    "file_name": "Hungary_DOUGLAS_HU_NEW|sp|BRANDS_JUICE|sp|BEAUTY_JUICE|sp|BEAUTY"
  },
  {
    "country": "Hungary",
    "retailer": "Douglas_HU",
    "parsing_config": "./retailer_config/Douglas/douglas_parsing.json",
    "gcloud_path": "crawl_data/Hungary/Douglas_HU/",
    "department": "New Brands",
    "category": "KERASTASIS",
    "page": "KERASTASIS",
    "page_url": "https://www.douglas.hu/c/uj-markak/kerastase/",
    "file_name": "Hungary_DOUGLAS_HU_NEW|sp|BRANDS_KERASTASIS_KERASTASIS"
  },
  {
    "country": "Hungary",
    "retailer": "Douglas_HU",
    "parsing_config": "./retailer_config/Douglas/douglas_parsing.json",
    "gcloud_path": "crawl_data/Hungary/Douglas_HU/",
    "department": "New Brands",
    "category": "KORLOFF",
    "page": "KORLOFF",
    "page_url": "https://www.douglas.hu/c/uj-markak/korloff/",
    "file_name": "Hungary_DOUGLAS_HU_NEW|sp|BRANDS_KORLOFF_KORLOFF"
  },
  {
    "country": "Hungary",
    "retailer": "Douglas_HU",
    "parsing_config": "./retailer_config/Douglas/douglas_parsing.json",
    "gcloud_path": "crawl_data/Hungary/Douglas_HU/",
    "department": "New Brands",
    "category": "MARC JACOBS",
    "page": "MARC JACOBS",
    "page_url": "https://www.douglas.hu/c/uj-markak/marc-jacobs/",
    "file_name": "Hungary_DOUGLAS_HU_NEW|sp|BRANDS_MARC|sp|JACOBS_MARC|sp|JACOBS"
  },
  {
    "country": "Hungary",
    "retailer": "Douglas_HU",
    "parsing_config": "./retailer_config/Douglas/douglas_parsing.json",
    "gcloud_path": "crawl_data/Hungary/Douglas_HU/",
    "department": "New Brands",
    "category": "MOKOSH COSMETICS",
    "page": "MOKOSH COSMETICS",
    "page_url": "https://www.douglas.hu/c/uj-markak/mokosh-cosmetics/",
    "file_name": "Hungary_DOUGLAS_HU_NEW|sp|BRANDS_MOKOSH|sp|COSMETICS_MOKOSH|sp|COSMETICS"
  },
  {
    "country": "Hungary",
    "retailer": "Douglas_HU",
    "parsing_config": "./retailer_config/Douglas/douglas_parsing.json",
    "gcloud_path": "crawl_data/Hungary/Douglas_HU/",
    "department": "New Brands",
    "category": "NAJ OLEARI",
    "page": "NAJ OLEARI",
    "page_url": "https://www.douglas.hu/c/uj-markak/naj-oleari/",
    "file_name": "Hungary_DOUGLAS_HU_NEW|sp|BRANDS_NAJ|sp|OLEARI_NAJ|sp|OLEARI"
  },
  {
    "country": "Hungary",
    "retailer": "Douglas_HU",
    "parsing_config": "./retailer_config/Douglas/douglas_parsing.json",
    "gcloud_path": "crawl_data/Hungary/Douglas_HU/",
    "department": "New Brands",
    "category": "NUXE",
    "page": "NUXE",
    "page_url": "https://www.douglas.hu/c/uj-markak/nuxe/",
    "file_name": "Hungary_DOUGLAS_HU_NEW|sp|BRANDS_NUXE_NUXE"
  },
  {
    "country": "Hungary",
    "retailer": "Douglas_HU",
    "parsing_config": "./retailer_config/Douglas/douglas_parsing.json",
    "gcloud_path": "crawl_data/Hungary/Douglas_HU/",
    "department": "New Brands",
    "category": "PIXI",
    "page": "PIXI",
    "page_url": "https://www.douglas.hu/c/uj-markak/pixi/",
    "file_name": "Hungary_DOUGLAS_HU_NEW|sp|BRANDS_PIXI_PIXI"
  },
  {
    "country": "Hungary",
    "retailer": "Douglas_HU",
    "parsing_config": "./retailer_config/Douglas/douglas_parsing.json",
    "gcloud_path": "crawl_data/Hungary/Douglas_HU/",
    "department": "New Brands",
    "category": "PHILIP PLEIN",
    "page": "PHILIP PLEIN",
    "page_url": "https://www.douglas.hu/c/uj-markak/philipp-plein/",
    "file_name": "Hungary_DOUGLAS_HU_NEW|sp|BRANDS_PHILIP|sp|PLEIN_PHILIP|sp|PLEIN"
  },
  {
    "country": "Hungary",
    "retailer": "Douglas_HU",
    "parsing_config": "./retailer_config/Douglas/douglas_parsing.json",
    "gcloud_path": "crawl_data/Hungary/Douglas_HU/",
    "department": "New Brands",
    "category": "REVOX",
    "page": "REVOX",
    "page_url": "https://www.douglas.hu/c/uj-markak/revox/",
    "file_name": "Hungary_DOUGLAS_HU_NEW|sp|BRANDS_REVOX_REVOX"
  },
  {
    "country": "Hungary",
    "retailer": "Douglas_HU",
    "parsing_config": "./retailer_config/Douglas/douglas_parsing.json",
    "gcloud_path": "crawl_data/Hungary/Douglas_HU/",
    "department": "New Brands",
    "category": "RICHOULI",
    "page": "RICHOULI",
    "page_url": "https://www.douglas.hu/c/uj-markak/richouli/",
    "file_name": "Hungary_DOUGLAS_HU_NEW|sp|BRANDS_RICHOULI_RICHOULI"
  },
  {
    "country": "Hungary",
    "retailer": "Douglas_HU",
    "parsing_config": "./retailer_config/Douglas/douglas_parsing.json",
    "gcloud_path": "crawl_data/Hungary/Douglas_HU/",
    "department": "New Brands",
    "category": "TEAOLOGY",
    "page": "TEAOLOGY",
    "page_url": "https://www.douglas.hu/c/uj-markak/teaology/",
    "file_name": "Hungary_DOUGLAS_HU_NEW|sp|BRANDS_TEAOLOGY_TEAOLOGY"
  },
  {
    "country": "Hungary",
    "retailer": "Douglas_HU",
    "parsing_config": "./retailer_config/Douglas/douglas_parsing.json",
    "gcloud_path": "crawl_data/Hungary/Douglas_HU/",
    "department": "New Brands",
    "category": "BELIEVE",
    "page": "BELIEVE",
    "page_url": "https://www.douglas.hu/c/uj-markak/usu/",
    "file_name": "Hungary_DOUGLAS_HU_NEW|sp|BRANDS_BELIEVE_BELIEVE"
  },
  {
    "country": "Hungary",
    "retailer": "Douglas_HU",
    "parsing_config": "./retailer_config/Douglas/douglas_parsing.json",
    "gcloud_path": "crawl_data/Hungary/Douglas_HU/",
    "department": "Clean Beauty",
    "category": "Clean Beauty",
    "page": "Clean Beauty",
    "page_url": "https://www.douglas.hu/c/clean-beauty/",
    "file_name": "Hungary_DOUGLAS_HU_CLEAN|sp|BEAUTY_CLEAN|sp|BEAUTY_CLEAN|sp|BEAUTY"
  },
  {
    "country": "Hungary",
    "retailer": "Douglas_HU",
    "parsing_config": "./retailer_config/Douglas/douglas_parsing.json",
    "gcloud_path": "crawl_data/Hungary/Douglas_HU/",
    "department": "Clean Beauty",
    "category": "Perfumes",
    "page": "Perfumes",
    "page_url": "https://www.douglas.hu/c/clean-beauty/parfum/",
    "file_name": "Hungary_DOUGLAS_HU_CLEAN|sp|BEAUTY_PERFUME_PERFUME"
  },
  {
    "country": "Hungary",
    "retailer": "Douglas_HU",
    "parsing_config": "./retailer_config/Douglas/douglas_parsing.json",
    "gcloud_path": "crawl_data/Hungary/Douglas_HU/",
    "department": "Clean Beauty",
    "category": "Perfumes",
    "page": "Womens scents",
    "page_url": "https://www.douglas.hu/c/clean-beauty/parfum/noi-illatok/",
    "file_name": "Hungary_DOUGLAS_HU_CLEAN|sp|BEAUTY_PERFUME_Women|sq|s|sp|scents"
  },
  {
    "country": "Hungary",
    "retailer": "Douglas_HU",
    "parsing_config": "./retailer_config/Douglas/douglas_parsing.json",
    "gcloud_path": "crawl_data/Hungary/Douglas_HU/",
    "department": "Clean Beauty",
    "category": "Perfumes",
    "page": "Men's scents",
    "page_url": "https://www.douglas.hu/c/clean-beauty/parfum/ferfi-illatok/",
    "file_name": "Hungary_DOUGLAS_HU_CLEAN|sp|BEAUTY_PERFUME_Men|sq|s|sp|scents"
  },
  {
    "country": "Hungary",
    "retailer": "Douglas_HU",
    "parsing_config": "./retailer_config/Douglas/douglas_parsing.json",
    "gcloud_path": "crawl_data/Hungary/Douglas_HU/",
    "department": "Clean Beauty",
    "category": "Care",
    "page": "Care",
    "page_url": "https://www.douglas.hu/c/clean-beauty/apolas/",
    "file_name": "Hungary_DOUGLAS_HU_CLEAN|sp|BEAUTY_CARE_CARE"
  },
  {
    "country": "Hungary",
    "retailer": "Douglas_HU",
    "parsing_config": "./retailer_config/Douglas/douglas_parsing.json",
    "gcloud_path": "crawl_data/Hungary/Douglas_HU/",
    "department": "Clean Beauty",
    "category": "Care",
    "page": "Facial Care",
    "page_url": "https://www.douglas.hu/c/clean-beauty/apolas/arcapolas/",
    "file_name": "Hungary_DOUGLAS_HU_CLEAN|sp|BEAUTY_CARE_Facial|sp|care"
  },
  {
    "country": "Hungary",
    "retailer": "Douglas_HU",
    "parsing_config": "./retailer_config/Douglas/douglas_parsing.json",
    "gcloud_path": "crawl_data/Hungary/Douglas_HU/",
    "department": "Clean Beauty",
    "category": "Care",
    "page": "Bodycare",
    "page_url": "https://www.douglas.hu/c/clean-beauty/apolas/testapolas/",
    "file_name": "Hungary_DOUGLAS_HU_CLEAN|sp|BEAUTY_CARE_Body|sp|care"
  },
  {
    "country": "Hungary",
    "retailer": "Douglas_HU",
    "parsing_config": "./retailer_config/Douglas/douglas_parsing.json",
    "gcloud_path": "crawl_data/Hungary/Douglas_HU/",
    "department": "Clean Beauty",
    "category": "Care",
    "page": "Haircare",
    "page_url": "https://www.douglas.hu/c/clean-beauty/apolas/hajapolas/",
    "file_name": "Hungary_DOUGLAS_HU_CLEAN|sp|BEAUTY_CARE_Hair|sp|care"
  },
  {
    "country": "Hungary",
    "retailer": "Douglas_HU",
    "parsing_config": "./retailer_config/Douglas/douglas_parsing.json",
    "gcloud_path": "crawl_data/Hungary/Douglas_HU/",
    "department": "Clean Beauty",
    "category": "Make Up",
    "page": "MAKEUP",
    "page_url": "https://www.douglas.hu/c/clean-beauty/smink/",
    "file_name": "Hungary_DOUGLAS_HU_CLEAN|sp|BEAUTY_MAKEUP_MAKEUP"
  },
  {
    "country": "Hungary",
    "retailer": "Douglas_HU",
    "parsing_config": "./retailer_config/Douglas/douglas_parsing.json",
    "gcloud_path": "crawl_data/Hungary/Douglas_HU/",
    "department": "Clean Beauty",
    "category": "Make Up",
    "page": "Arc",
    "page_url": "https://www.douglas.hu/c/clean-beauty/smink/arc/",
    "file_name": "Hungary_DOUGLAS_HU_CLEAN|sp|BEAUTY_MAKEUP_Arc"
  },
  {
    "country": "Hungary",
    "retailer": "Douglas_HU",
    "parsing_config": "./retailer_config/Douglas/douglas_parsing.json",
    "gcloud_path": "crawl_data/Hungary/Douglas_HU/",
    "department": "Clean Beauty",
    "category": "Make Up",
    "page": "Eye",
    "page_url": "https://www.douglas.hu/c/clean-beauty/smink/szem/",
    "file_name": "Hungary_DOUGLAS_HU_CLEAN|sp|BEAUTY_MAKEUP_Eye"
  },
  {
    "country": "Hungary",
    "retailer": "Douglas_HU",
    "parsing_config": "./retailer_config/Douglas/douglas_parsing.json",
    "gcloud_path": "crawl_data/Hungary/Douglas_HU/",
    "department": "Clean Beauty",
    "category": "Make Up",
    "page": "Invite",
    "page_url": "https://www.douglas.hu/c/clean-beauty/smink/ajak/",
    "file_name": "Hungary_DOUGLAS_HU_CLEAN|sp|BEAUTY_MAKEUP_Invite"
  },
  {
    "country": "Hungary",
    "retailer": "Douglas_HU",
    "parsing_config": "./retailer_config/Douglas/douglas_parsing.json",
    "gcloud_path": "crawl_data/Hungary/Douglas_HU/",
    "department": "Clean Beauty",
    "category": "Make Up",
    "page": "Nail",
    "page_url": "https://www.douglas.hu/c/clean-beauty/smink/korom/",
    "file_name": "Hungary_DOUGLAS_HU_CLEAN|sp|BEAUTY_MAKEUP_Nail"
  },
  {
    "country": "Hungary",
    "retailer": "Douglas_HU",
    "parsing_config": "./retailer_config/Douglas/douglas_parsing.json",
    "gcloud_path": "crawl_data/Hungary/Douglas_HU/",
    "department": "Clean Beauty",
    "category": "Make Up",
    "page": "Accessories",
    "page_url": "https://www.douglas.hu/c/clean-beauty/smink/kiegeszitok/",
    "file_name": "Hungary_DOUGLAS_HU_CLEAN|sp|BEAUTY_MAKEUP_Accessories"
  }
]
